Workbook

Sheet VENTAS
A1: Reference | B1: number | C1: Document | D1: sku | E1: Product | F1: Brand | G1: Type | H1: Family | I1: Line | J1: Sub Line | K1: clientNumber | L1: Customer | M1: Route Name | N1: routeVendor | O1: Sales Rep | P1: Truck Name | Q1: routeDriver | R1: deliveryDate | S1: Month | T1: Year | U1: Orig. Qty. | V1: Quantity | W1: Unit | X1: actualCost | Y1: Cost | Z1: Total Weight | AA1: Sale | AB1: Margin | AC1: Discount (Promotions) | AD1: Out of Code | AE1: Good Return | AF1: No Charge | AG1: quantity | AH1: Out of Code Units | AI1: Good Return Units | AJ1: noCharge
A2: 255-9010974 | B2: =VLOOKUP(A2,Sheet3!A:B,2,0) -> INV-205-2966 | C2: Invoice | D2: 92177 | E2: POCAS BUBLE T MATCHA 16.5/24CT | F2: POCAS | G2: BEBIDAS | H2: ------ | I2: ------ | J2: ------ | K2: 10406 | L2: Chevron #093679 | M2: 255 - Carlos Morales | N2: 205 | O2: Carlos Morales | P2: Sunmex Truck - 156 | Q2: 104 | R2: 02/16/2026 | S2: 02 | T2: 2026 | U2: 24 | V2: 24 | W2: UNIT(S) | X2: 1.89 | Y2: 1.14583 | Z2: 0 | AA2: 45.36 | AB2: 39.37% | AC2: 0 | AD2: 0 | AE2: 0 | AF2: 0 | AG2: 24 | AH2: 0 | AI2: 0 | AJ2: 0
A3: 255-9010974 | B3: =VLOOKUP(A3,Sheet3!A:B,2,0) -> INV-205-2966 | C3: Invoice | D3: 30937 | E3: SAB CHETO FLAMIN HOT 145G | F3: SABRITAS | G3: BOTANAS | H3: MAIZ | I3: CON QUESO | J3: CON CHILE | K3: 10406 | L3: Chevron #093679 | M3: 255 - Carlos Morales | N3: 205 | O3: Carlos Morales | P3: Sunmex Truck - 156 | Q3: 104 | R3: 02/16/2026 | S3: 02 | T3: 2026 | U3: 10 | V3: 10 | W3: UNIT(S) | X3: 2.79 | Y3: 1.99 | Z3: 0 | AA3: 27.9 | AB3: 28.67% | AC3: 0 | AD3: 0 | AE3: 0 | AF3: 0 | AG3: 10 | AH3: 0 | AI3: 0 | AJ3: 0
A4: 255-9010974 | B4: =VLOOKUP(A4,Sheet3!A:B,2,0) -> INV-205-2966 | C4: Invoice | D4: 19230 | E4: PARR ALOE WATERMELON 500M/20CT | F4: PARROT | G4: BEBIDAS | H4: JUGO DE FRUTAS | I4: ALOE VERA | J4: JUGO DE FRUTAS | K4: 10406 | L4: Chevron #093679 | M4: 255 - Carlos Morales | N4: 205 | O4: Carlos Morales | P4: Sunmex Truck - 156 | Q4: 104 | R4: 02/16/2026 | S4: 02 | T4: 2026 | U4: 20 | V4: 20 | W4: UNIT(S) | X4: 1.29 | Y4: 0.86 | Z4: 0 | AA4: 25.8 | AB4: 33.33% | AC4: 0 | AD4: 0 | AE4: 0 | AF4: 0 | AG4: 20 | AH4: 0 | AI4: 0 | AJ4: 0
A5: 255-9010974 | B5: =VLOOKUP(A5,Sheet3!A:B,2,0) -> INV-205-2966 | C5: Invoice | D5: 19207 | E5: PARR ALOE STRAWBERRY 500M/20CT | F5: PARROT | G5: BEBIDAS | H5: JUGO DE FRUTAS | I5: ALOE VERA | J5: JUGO DE FRUTAS | K5: 10406 | L5: Chevron #093679 | M5: 255 - Carlos Morales | N5: 205 | O5: Carlos Morales | P5: Sunmex Truck - 156 | Q5: 104 | R5: 02/16/2026 | S5: 02 | T5: 2026 | U5: 20 | V5: 20 | W5: UNIT(S) | X5: 1.29 | Y5: 0.86 | Z5: 0 | AA5: 25.8 | AB5: 33.33% | AC5: 0 | AD5: 0 | AE5: 0 | AF5: 0 | AG5: 20 | AH5: 0 | AI5: 0 | AJ5: 0
A6: 255-9010974 | B6: =VLOOKUP(A6,Sheet3!A:B,2,0) -> INV-205-2966 | C6: Invoice | D6: 66860 | E6: JUMEX CAN COCO-PINEAP 16OZ/12CT | F6: JUMEX | G6: BEBIDAS | H6: JUGO DE FRUTAS | I6: JUGO DE FRUTAS | J6: JUGO DE FRUTAS | K6: 10406 | L6: Chevron #093679 | M6: 255 - Carlos Morales | N6: 205 | O6: Carlos Morales | P6: Sunmex Truck - 156 | Q6: 104 | R6: 02/16/2026 | S6: 02 | T6: 2026 | U6: 12 | V6: 12 | W6: UNIT(S) | X6: 1.59 | Y6: 1.06 | Z6: 0 | AA6: 19.08 | AB6: 33.33% | AC6: 0 | AD6: 0 | AE6: 0 | AF6: 0 | AG6: 12 | AH6: 0 | AI6: 0 | AJ6: 0
A7: 255-9010974 | B7: =VLOOKUP(A7,Sheet3!A:B,2,0) -> INV-205-2966 | C7: Invoice | D7: 13976 | E7: DIANDI COYOTA CAJETA 9.52/14CT | F7: DIANDI | G7: PANES | H7: COYOTAS | I7: RELLENOS | J7: CAJETA | K7: 10406 | L7: Chevron #093679 | M7: 255 - Carlos Morales | N7: 205 | O7: Carlos Morales | P7: Sunmex Truck - 156 | Q7: 104 | R7: 02/16/2026 | S7: 02 | T7: 2026 | U7: 5 | V7: 5 | W7: UNIT(S) | X7: 2.53 | Y7: 1.68 | Z7: 0 | AA7: 12.65 | AB7: 33.6% | AC7: 0 | AD7: 0 | AE7: 0 | AF7: 0 | AG7: 5 | AH7: 0 | AI7: 0 | AJ7: 0
A8: 255-9010974 | B8: =VLOOKUP(A8,Sheet3!A:B,2,0) -> INV-205-2966 | C8: Invoice | D8: 13907 | E8: DIANDI COYOTA DUL LECH 9.52/14CT | F8: DIANDI | G8: PANES | H8: COYOTAS | I8: RELLENOS | J8: DULCE DE LECHE | K8: 10406 | L8: Chevron #093679 | M8: 255 - Carlos Morales | N8: 205 | O8: Carlos Morales | P8: Sunmex Truck - 156 | Q8: 104 | R8: 02/16/2026 | S8: 02 | T8: 2026 | U8: 5 | V8: 5 | W8: UNIT(S) | X8: 2.53 | Y8: 1.68 | Z8: 0 | AA8: 12.65 | AB8: 33.6% | AC8: 0 | AD8: 0 | AE8: 0 | AF8: 0 | AG8: 5 | AH8: 0 | AI8: 0 | AJ8: 0
A9: 255-9010974 | B9: =VLOOKUP(A9,Sheet3!A:B,2,0) -> INV-205-2966 | C9: Invoice | D9: 16580 | E9: GAMESA CREMAX FRESA 90G | F9: GAMESA | G9: GALLETAS | H9: GALLETAS DULCES | I9: ------ | J9: ------ | K9: 10406 | L9: Chevron #093679 | M9: 255 - Carlos Morales | N9: 205 | O9: Carlos Morales | P9: Sunmex Truck - 156 | Q9: 104 | R9: 02/16/2026 | S9: 02 | T9: 2026 | U9: 5 | V9: 5 | W9: UNIT(S) | X9: 2.09 | Y9: 1.35 | Z9: 0 | AA9: 10.45 | AB9: 35.41% | AC9: 0 | AD9: 0 | AE9: 0 | AF9: 0 | AG9: 5 | AH9: 0 | AI9: 0 | AJ9: 0
A10: 255-9010974 | B10: =VLOOKUP(A10,Sheet3!A:B,2,0) -> INV-205-2966 | C10: Invoice | D10: 16566 | E10: GAMESA CREMAX CHOCOLATE 90G | F10: GAMESA | G10: GALLETAS | H10: GALLETAS DULCES | I10: ------ | J10: ------ | K10: 10406 | L10: Chevron #093679 | M10: 255 - Carlos Morales | N10: 205 | O10: Carlos Morales | P10: Sunmex Truck - 156 | Q10: 104 | R10: 02/16/2026 | S10: 02 | T10: 2026 | U10: 5 | V10: 5 | W10: UNIT(S) | X10: 2.09 | Y10: 1.35 | Z10: 0 | AA10: 10.45 | AB10: 35.41% | AC10: 0 | AD10: 0 | AE10: 0 | AF10: 0 | AG10: 5 | AH10: 0 | AI10: 0 | AJ10: 0
A11: 255-9010974 | B11: =VLOOKUP(A11,Sheet3!A:B,2,0) -> INV-205-2966 | C11: Invoice | D11: 22502 | E11: GAMESA EMPERADOR PIRUETA 115G | F11: GAMESA | G11: GALLETAS | H11: GALLETAS DULCES | I11: ------ | J11: ------ | K11: 10406 | L11: Chevron #093679 | M11: 255 - Carlos Morales | N11: 205 | O11: Carlos Morales | P11: Sunmex Truck - 156 | Q11: 104 | R11: 02/16/2026 | S11: 02 | T11: 2026 | U11: 5 | V11: 5 | W11: UNIT(S) | X11: 2.09 | Y11: 1.4 | Z11: 0 | AA11: 10.45 | AB11: 33.01% | AC11: 0 | AD11: 0 | AE11: 0 | AF11: 0 | AG11: 5 | AH11: 0 | AI11: 0 | AJ11: 0
A12: 255-9010974 | B12: =VLOOKUP(A12,Sheet3!A:B,2,0) -> INV-205-2966 | C12: Invoice | D12: 35726 | E12: GAMESA ARCOIRIS 75G | F12: GAMESA | G12: GALLETAS | H12: GALLETAS DULCES | I12: ------ | J12: ------ | K12: 10406 | L12: Chevron #093679 | M12: 255 - Carlos Morales | N12: 205 | O12: Carlos Morales | P12: Sunmex Truck - 156 | Q12: 104 | R12: 02/16/2026 | S12: 02 | T12: 2026 | U12: 5 | V12: 5 | W12: UNIT(S) | X12: 2.09 | Y12: 1.4 | Z12: 0 | AA12: 10.45 | AB12: 33.01% | AC12: 0 | AD12: 0 | AE12: 0 | AF12: 0 | AG12: 5 | AH12: 0 | AI12: 0 | AJ12: 0
A13: 255-9010974 | B13: =VLOOKUP(A13,Sheet3!A:B,2,0) -> INV-205-2966 | C13: Invoice | D13: 23608 | E13: GAMESA MARAVILLAS 112G | F13: GAMESA | G13: GALLETAS | H13: GALLETAS DULCES | I13: ------ | J13: ------ | K13: 10406 | L13: Chevron #093679 | M13: 255 - Carlos Morales | N13: 205 | O13: Carlos Morales | P13: Sunmex Truck - 156 | Q13: 104 | R13: 02/16/2026 | S13: 02 | T13: 2026 | U13: 5 | V13: 5 | W13: UNIT(S) | X13: 2.09 | Y13: 1.4 | Z13: 0 | AA13: 10.45 | AB13: 33.01% | AC13: 0 | AD13: 0 | AE13: 0 | AF13: 0 | AG13: 5 | AH13: 0 | AI13: 0 | AJ13: 0
... A1202: 256-9009423 | B1202: =VLOOKUP(A1202,Sheet3!A:B,2,0) -> INV-206-3015 | C1202: Invoice | D1202: 14745 | E1202: COCA COLA 3 LITER / 6CT | F1202: COCA COLA FAMILIAR | G1202: BEBIDAS | H1202: BEBIDA CON SABOR | I1202: BEBIDA CON GAS | J1202: BEBIDA CON GAS | K1202: 10578 | L1202: El Alamo Supercarniceria at Chandler | M1202: 256 - Ana Ibarra | N1202: 206 | O1202: Ana Ibarra | P1202: Sunmex Truck - 151 | Q1202: 101 | R1202: 02/16/2026 | S1202: 02 | T1202: 2026 | U1202: 6 | V1202: 6 | W1202: UNIT(S) | X1202: 4.49 | Y1202: 3.183333 | Z1202: 0 | AA1202: 26.94 | AB1202: 29.1% | AC1202: 0 | AD1202: 0 | AE1202: 0 | AF1202: 0 | AG1202: 6 | AH1202: 0 | AI1202: 0 | AJ1202: 0
A1203: 379-000679 | B1203: =VLOOKUP(A1203,Sheet3!A:B,2,0) -> INV-001-3075 | C1203: Invoice | D1203: 31118 | E1203: SAB FRITO CHILE LIMON 170G | F1203: SABRITAS | G1203: BOTANAS | H1203: MAIZ | I1203: CON CHILE | J1203: CON LIMON | K1203: 10976 | L1203: Phx Samples | M1203: 379 - Venta Piso | N1203: 001 | O1203: NoCharge Samples | Q1203: 001 | R1203: 02/16/2026 | S1203: 02 | T1203: 2026 | U1203: 18 | V1203: 18 | W1203: UNIT(S) | X1203: 1.99 | Y1203: 1.99 | Z1203: 0 | AA1203: 0 | AB1203: 0 | AC1203: 35.82 | AD1203: 0 | AE1203: 0 | AF1203: 35.82 | AG1203: 0 | AH1203: 0 | AI1203: 0 | AJ1203: 18
A1204: 379-000679 | B1204: =VLOOKUP(A1204,Sheet3!A:B,2,0) -> INV-001-3075 | C1204: Invoice | D1204: 30920 | E1204: SAB CHETO BOLITAS 110G | F1204: SABRITAS | G1204: BOTANAS | H1204: MAIZ | I1204: CON QUESO | J1204: CON CHILE | K1204: 10976 | L1204: Phx Samples | M1204: 379 - Venta Piso | N1204: 001 | O1204: NoCharge Samples | Q1204: 001 | R1204: 02/16/2026 | S1204: 02 | T1204: 2026 | U1204: 40 | V1204: 40 | W1204: UNIT(S) | X1204: 1.99 | Y1204: 1.99 | Z1204: 0 | AA1204: 0 | AB1204: 0 | AC1204: 79.6 | AD1204: 0 | AE1204: 0 | AF1204: 79.6 | AG1204: 0 | AH1204: 0 | AI1204: 0 | AJ1204: 40
A1205: 379-000679 | B1205: =VLOOKUP(A1205,Sheet3!A:B,2,0) -> INV-001-3075 | C1205: Invoice | D1205: 21269 | E1205: BARCEL RUNNER 200GR | F1205: BARCEL | G1205: BOTANAS | H1205: MAIZ | I1205: ------ | J1205: ------ | K1205: 10976 | L1205: Phx Samples | M1205: 379 - Venta Piso | N1205: 001 | O1205: NoCharge Samples | Q1205: 001 | R1205: 02/16/2026 | S1205: 02 | T1205: 2026 | U1205: 6 | V1205: 6 | W1205: UNIT(S) | X1205: 2.55 | Y1205: 2.55 | Z1205: 0 | AA1205: 0 | AB1205: 0 | AC1205: 15.3 | AD1205: 0 | AE1205: 0 | AF1205: 15.3 | AG1205: 0 | AH1205: 0 | AI1205: 0 | AJ1205: 6
A1206: 379-000679 | B1206: =VLOOKUP(A1206,Sheet3!A:B,2,0) -> INV-001-3075 | C1206: Invoice | D1206: 44405 | E1206: SAB PAKETAXO DARK 208GR | F1206: SABRITAS | G1206: BOTANAS | H1206: ------ | I1206: ------ | J1206: ------ | K1206: 10976 | L1206: Phx Samples | M1206: 379 - Venta Piso | N1206: 001 | O1206: NoCharge Samples | Q1206: 001 | R1206: 02/16/2026 | S1206: 02 | T1206: 2026 | U1206: 7 | V1206: 7 | W1206: UNIT(S) | X1206: 3.05 | Y1206: 3.05 | Z1206: 0 | AA1206: 0 | AB1206: 0 | AC1206: 21.35 | AD1206: 0 | AE1206: 0 | AF1206: 21.35 | AG1206: 0 | AH1206: 0 | AI1206: 0 | AJ1206: 7
A1207: 259-9000560 | B1207: =VLOOKUP(A1207,Sheet3!A:B,2,0) -> INV-001-3055 | C1207: Invoice | D1207: 31064 | E1207: SAB DORITO NACHOS 146G | F1207: SABRITAS | G1207: BOTANAS | H1207: MAIZ | I1207: CON QUESO | J1207: CON CHILE | K1207: 11719 | L1207: NC Distributor LLC. | M1207: 259 - Venta Administrativa | N1207: 001 | O1207: Ventas Administrativas | P1207: Sunmex Truck - 152 | Q1207: 001 | R1207: 02/17/2026 | S1207: 02 | T1207: 2026 | U1207: 552 | V1207: 552 | W1207: UNIT(S) | X1207: 2.1 | Y1207: 1.99 | Z1207: 0 | AA1207: 1159.2 | AB1207: 38.1% | AC1207: 380.88 | AD1207: 0 | AE1207: 0 | AF1207: 0 | AG1207: 552 | AH1207: 0 | AI1207: 0 | AJ1207: 0
A1208: 259-9000560 | B1208: =VLOOKUP(A1208,Sheet3!A:B,2,0) -> INV-001-3055 | C1208: Invoice | D1208: 30937 | E1208: SAB CHETO FLAMIN HOT 145G | F1208: SABRITAS | G1208: BOTANAS | H1208: MAIZ | I1208: CON QUESO | J1208: CON CHILE | K1208: 11719 | L1208: NC Distributor LLC. | M1208: 259 - Venta Administrativa | N1208: 001 | O1208: Ventas Administrativas | P1208: Sunmex Truck - 152 | Q1208: 001 | R1208: 02/17/2026 | S1208: 02 | T1208: 2026 | U1208: 300 | V1208: 300 | W1208: UNIT(S) | X1208: 2.1 | Y1208: 1.99 | Z1208: 0 | AA1208: 630 | AB1208: 38.1% | AC1208: 207 | AD1208: 0 | AE1208: 0 | AF1208: 0 | AG1208: 300 | AH1208: 0 | AI1208: 0 | AJ1208: 0
A1209: 259-9000560 | B1209: =VLOOKUP(A1209,Sheet3!A:B,2,0) -> INV-001-3055 | C1209: Invoice | D1209: 30869 | E1209: SAB TOSTITO SALSA 175G | F1209: SABRITAS | G1209: BOTANAS | H1209: MAIZ | I1209: CON SALSA VERDE | J1209: CON SABOR | K1209: 11719 | L1209: NC Distributor LLC. | M1209: 259 - Venta Administrativa | N1209: 001 | O1209: Ventas Administrativas | P1209: Sunmex Truck - 152 | Q1209: 001 | R1209: 02/17/2026 | S1209: 02 | T1209: 2026 | U1209: 286 | V1209: 286 | W1209: UNIT(S) | X1209: 2.1 | Y1209: 1.99 | Z1209: 0 | AA1209: 600.6 | AB1209: 38.1% | AC1209: 197.34 | AD1209: 0 | AE1209: 0 | AF1209: 0 | AG1209: 286 | AH1209: 0 | AI1209: 0 | AJ1209: 0
A1210: 259-9000560 | B1210: =VLOOKUP(A1210,Sheet3!A:B,2,0) -> INV-001-3055 | C1210: Invoice | D1210: 51062 | E1210: SAB FRITO CHORIZO 170G | F1210: SABRITAS | G1210: BOTANAS | H1210: MAIZ | I1210: CON CHORIZO | J1210: CON CHIPOTLE | K1210: 11719 | L1210: NC Distributor LLC. | M1210: 259 - Venta Administrativa | N1210: 001 | O1210: Ventas Administrativas | P1210: Sunmex Truck - 152 | Q1210: 001 | R1210: 02/17/2026 | S1210: 02 | T1210: 2026 | U1210: 44 | V1210: 44 | W1210: UNIT(S) | X1210: 2.1 | Y1210: 1.99 | Z1210: 0 | AA1210: 92.4 | AB1210: 38.1% | AC1210: 30.36 | AD1210: 0 | AE1210: 0 | AF1210: 0 | AG1210: 44 | AH1210: 0 | AI1210: 0 | AJ1210: 0
A1211: 259-9000560 | B1211: =VLOOKUP(A1211,Sheet3!A:B,2,0) -> INV-001-3055 | C1211: Invoice | D1211: 31125 | E1211: SAB FRITO LIMON SAL 170G | F1211: SABRITAS | G1211: BOTANAS | H1211: MAIZ | I1211: CON SAL | J1211: CON LIMON | K1211: 11719 | L1211: NC Distributor LLC. | M1211: 259 - Venta Administrativa | N1211: 001 | O1211: Ventas Administrativas | P1211: Sunmex Truck - 152 | Q1211: 001 | R1211: 02/17/2026 | S1211: 02 | T1211: 2026 | U1211: 44 | V1211: 44 | W1211: UNIT(S) | X1211: 2.1 | Y1211: 1.99 | Z1211: 0 | AA1211: 92.4 | AB1211: 38.1% | AC1211: 30.36 | AD1211: 0 | AE1211: 0 | AF1211: 0 | AG1211: 44 | AH1211: 0 | AI1211: 0 | AJ1211: 0
A1212: 256-9009433 | B1212: =VLOOKUP(A1212,Sheet3!A:B,2,0) -> INV-206-3023 | C1212: Invoice | D1212: 16548 | E1212: NESCAFE DOLCA 170G/15CT | F1212: NESCAFE | G1212: ABARROTES | H1212: CAFE | I1212: INSTANTANEAS | J1212: ------ | K1212: 11716 | L1212: Carniceria Sonora #4 | M1212: 256 - Ana Ibarra | N1212: 206 | O1212: Ana Ibarra | P1212: Sunmex Truck - 156 | Q1212: 104 | R1212: 02/17/2026 | S1212: 02 | T1212: 2026 | U1212: 15 | V1212: 15 | W1212: UNIT(S) | X1212: 7.55 | Y1212: 5.86666 | Z1212: 0 | AA1212: 113.25 | AB1212: 33.42% | AC1212: 12.6 | AD1212: 0 | AE1212: 0 | AF1212: 0 | AG1212: 15 | AH1212: 0 | AI1212: 0 | AJ1212: 0
A1213: 256-9009433 | B1213: =VLOOKUP(A1213,Sheet3!A:B,2,0) -> INV-206-3023 | C1213: Invoice | D1213: 14745 | E1213: COCA COLA 3 LITER / 6CT | F1213: COCA COLA FAMILIAR | G1213: BEBIDAS | H1213: BEBIDA CON SABOR | I1213: BEBIDA CON GAS | J1213: BEBIDA CON GAS | K1213: 11716 | L1213: Carniceria Sonora #4 | M1213: 256 - Ana Ibarra | N1213: 206 | O1213: Ana Ibarra | P1213: Sunmex Truck - 156 | Q1213: 104 | R1213: 02/17/2026 | S1213: 02 | T1213: 2026 | U1213: 24 | V1213: 24 | W1213: UNIT(S) | X1213: 3.99 | Y1213: 3.183333 | Z1213: 0 | AA1213: 95.76 | AB1213: 32.75% | AC1213: 12 | AD1213: 0 | AE1213: 0 | AF1213: 0 | AG1213: 24 | AH1213: 0 | AI1213: 0 | AJ1213: 0
A1214: 256-9009433 | B1214: =VLOOKUP(A1214,Sheet3!A:B,2,0) -> INV-206-3023 | C1214: Invoice | D1214: 38206 | E1214: KIDSM YO YO MANIA 12CT | F1214: KIDSMANIA | G1214: JUGUETES | H1214: ------ | I1214: ------ | J1214: ------ | K1214: 11716 | L1214: Carniceria Sonora #4 | M1214: 256 - Ana Ibarra | N1214: 206 | O1214: Ana Ibarra | P1214: Sunmex Truck - 156 | Q1214: 104 | R1214: 02/17/2026 | S1214: 02 | T1214: 2026 | U1214: 4 | V1214: 4 | W1214: UNIT(S) | X1214: 16.01 | Y1214: 11 | Z1214: 0 | AA1214: 64.04 | AB1214: 37.41% | AC1214: 3.92 | AD1214: 0 | AE1214: 0 | AF1214: 0 | AG1214: 4 | AH1214: 0 | AI1214: 0 | AJ1214: 0
A1215: 256-9009433 | B1215: =VLOOKUP(A1215,Sheet3!A:B,2,0) -> INV-206-3023 | C1215: Invoice | D1215: 10577 | E1215: 1-2-3 VEGETAL OIL 1LT/15CT | F1215: 1-2-3 | G1215: ABARROTES | H1215: ACEITE | I1215: VEGETAL | J1215: COMESTIBLE | K1215: 11716 | L1215: Carniceria Sonora #4 | M1215: 256 - Ana Ibarra | N1215: 206 | O1215: Ana Ibarra | P1215: Sunmex Truck - 156 | Q1215: 104 | R1215: 02/17/2026 | S1215: 02 | T1215: 2026 | U1215: 15 | V1215: 15 | W1215: UNIT(S) | X1215: 3.59 | Y1215: 2.89 | Z1215: 0 | AA1215: 53.85 | AB1215: 30.64% | AC1215: 6 | AD1215: 0 | AE1215: 0 | AF1215: 0 | AG1215: 15 | AH1215: 0 | AI1215: 0 | AJ1215: 0
A1216: 256-9009433 | B1216: =VLOOKUP(A1216,Sheet3!A:B,2,0) -> INV-206-3023 | C1216: Invoice | D1216: 10374 | E1216: TOPO CHICO MINERAL 355ML/24CT | F1216: TOPO CHICO | G1216: BEBIDAS | H1216: BEBIDA GASEOSA | I1216: ------ | J1216: ------ | K1216: 11716 | L1216: Carniceria Sonora #4 | M1216: 256 - Ana Ibarra | N1216: 206 | O1216: Ana Ibarra | P1216: Sunmex Truck - 156 | Q1216: 104 | R1216: 02/17/2026 | S1216: 02 | T1216: 2026 | U1216: 24 | V1216: 24 | W1216: UNIT(S) | X1216: 1.64 | Y1216: 1.28 | Z1216: 0 | AA1216: 39.36 | AB1216: 32.93% | AC1216: 4.32 | AD1216: 0 | AE1216: 0 | AF1216: 0 | AG1216: 24 | AH1216: 0 | AI1216: 0 | AJ1216: 0
A1217: 256-9009433 | B1217: =VLOOKUP(A1217,Sheet3!A:B,2,0) -> INV-206-3023 | C1217: Invoice | D1217: 19216 | E1217: PARR ALOE MANGO 1.5 LT/12CT | F1217: PARROT | G1217: BEBIDAS | H1217: JUGO DE FRUTAS | I1217: ALOE VERA | J1217: JUGO DE FRUTAS | K1217: 11716 | L1217: Carniceria Sonora #4 | M1217: 256 - Ana Ibarra | N1217: 206 | O1217: Ana Ibarra | P1217: Sunmex Truck - 156 | Q1217: 104 | R1217: 02/17/2026 | S1217: 02 | T1217: 2026 | U1217: 12 | V1217: 12 | W1217: UNIT(S) | X1217: 2.7 | Y1217: 2.079166 | Z1217: 0 | AA1217: 32.4 | AB1217: 33.73% | AC1217: 3.48 | AD1217: 0 | AE1217: 0 | AF1217: 0 | AG1217: 12 | AH1217: 0 | AI1217: 0 | AJ1217: 0
A1218: 256-9009433 | B1218: =VLOOKUP(A1218,Sheet3!A:B,2,0) -> INV-206-3023 | C1218: Invoice | D1218: 19217 | E1218: PARR ALOE POMEGRANATE 1.5LT/12CT | F1218: PARROT | G1218: BEBIDAS | H1218: JUGO DE FRUTAS | I1218: ALOE VERA | J1218: JUGO DE FRUTAS | K1218: 11716 | L1218: Carniceria Sonora #4 | M1218: 256 - Ana Ibarra | N1218: 206 | O1218: Ana Ibarra | P1218: Sunmex Truck - 156 | Q1218: 104 | R1218: 02/17/2026 | S1218: 02 | T1218: 2026 | U1218: 12 | V1218: 12 | W1218: UNIT(S) | X1218: 2.7 | Y1218: 2.07916 | Z1218: 0 | AA1218: 32.4 | AB1218: 33.73% | AC1218: 3.48 | AD1218: 0 | AE1218: 0 | AF1218: 0 | AG1218: 12 | AH1218: 0 | AI1218: 0 | AJ1218: 0
A1219: 256-9009433 | B1219: =VLOOKUP(A1219,Sheet3!A:B,2,0) -> INV-206-3023 | C1219: Invoice | D1219: 13457 | E1219: DIANDI MINI BESITO NUEZ 160/12CT | F1219: DIANDI GALLETAS | G1219: GALLETAS | H1219: ------ | I1219: ------ | J1219: ------ | K1219: 11716 | L1219: Carniceria Sonora #4 | M1219: 256 - Ana Ibarra | N1219: 206 | O1219: Ana Ibarra | P1219: Sunmex Truck - 156 | Q1219: 104 | R1219: 02/17/2026 | S1219: 02 | T1219: 2026 | U1219: 12 | V1219: 12 | W1219: UNIT(S) | X1219: 2.49 | Y1219: 2.1 | Z1219: 0 | AA1219: 29.88 | AB1219: 15.66% | AC1219: 0 | AD1219: 0 | AE1219: 0 | AF1219: 0 | AG1219: 12 | AH1219: 0 | AI1219: 0 | AJ1219: 0
A1220: 256-9009433 | B1220: =VLOOKUP(A1220,Sheet3!A:B,2,0) -> INV-206-3023 | C1220: Invoice | D1220: 15918 | E1220: VIVE 100 ORIGINAL 600ML/24CT | F1220: VIVE 100 | G1220: BEBIDAS | H1220: ENERGETICOS | I1220: BEBIDA CON SABOR | J1220: BEBIDA CON SABOR | K1220: 11716 | L1220: Carniceria Sonora #4 | M1220: 256 - Ana Ibarra | N1220: 206 | O1220: Ana Ibarra | P1220: Sunmex Truck - 156 | Q1220: 104 | R1220: 02/17/2026 | S1220: 02 | T1220: 2026 | U1220: 24 | V1220: 24 | W1220: UNIT(S) | X1220: 1.2 | Y1220: 0.81 | Z1220: 0 | AA1220: 28.8 | AB1220: 43.33% | AC1220: 3.12 | AD1220: 0 | AE1220: 0 | AF1220: 0 | AG1220: 24 | AH1220: 0 | AI1220: 0 | AJ1220: 0
A1221: 256-9009433 | B1221: =VLOOKUP(A1221,Sheet3!A:B,2,0) -> INV-206-3023 | C1221: Invoice | D1221: 30003 | E1221: LUC GUMIES WATERMELN 12UN 4.58 | F1221: LUCAS | G1221: DULCES | H1221: ------ | I1221: ------ | J1221: ------ | K1221: 11716 | L1221: Carniceria Sonora #4 | M1221: 256 - Ana Ibarra | N1221: 206 | O1221: Ana Ibarra | P1221: Sunmex Truck - 156 | Q1221: 104 | R1221: 02/17/2026 | S1221: 02 | T1221: 2026 | U1221: 1 | V1221: 1 | W1221: UNIT(S) | X1221: 26.09 | Y1221: 19 | Z1221: 0 | AA1221: 26.09 | AB1221: 38.29% | AC1221: 2.9 | AD1221: 0 | AE1221: 0 | AF1221: 0 | AG1221: 1 | AH1221: 0 | AI1221: 0 | AJ1221: 0
A1222: 256-9009433 | B1222: =VLOOKUP(A1222,Sheet3!A:B,2,0) -> INV-206-3023 | C1222: Invoice | D1222: 30016 | E1222: HUICHOL TRADITIONAL 6.5OZ/24CT | F1222: SALSA HUICHOL | G1222: ABARROTES | H1222: SALSAS | I1222: CON CHILE | J1222: CON CHILE | K1222: 11716 | L1222: Carniceria Sonora #4 | M1222: 256 - Ana Ibarra | N1222: 206 | O1222: Ana Ibarra | P1222: Sunmex Truck - 156 | Q1222: 104 | R1222: 02/17/2026 | S1222: 02 | T1222: 2026 | U1222: 24 | V1222: 24 | W1222: UNIT(S) | X1222: 1.07 | Y1222: 0.79 | Z1222: 0 | AA1222: 25.68 | AB1222: 37.38% | AC1222: 2.88 | AD1222: 0 | AE1222: 0 | AF1222: 0 | AG1222: 24 | AH1222: 0 | AI1222: 0 | AJ1222: 0
A1223: 256-9009433 | B1223: =VLOOKUP(A1223,Sheet3!A:B,2,0) -> INV-206-3023 | C1223: Invoice | D1223: 14813 | E1223: FRESCA TORONJA 3 LITER / 6CT | F1223: COCA COLA FAMILIAR | G1223: BEBIDAS | H1223: BEBIDA CON SABOR | I1223: BEBIDA CON GAS | J1223: BEBIDA CON GAS | K1223: 11716 | L1223: Carniceria Sonora #4 | M1223: 256 - Ana Ibarra | N1223: 206 | O1223: Ana Ibarra | P1223: Sunmex Truck - 156 | Q1223: 104 | R1223: 02/17/2026 | S1223: 02 | T1223: 2026 | U1223: 6 | V1223: 6 | W1223: UNIT(S) | X1223: 3.99 | Y1223: 3.183333 | Z1223: 0 | AA1223: 23.94 | AB1223: 32.75% | AC1223: 3 | AD1223: 0 | AE1223: 0 | AF1223: 0 | AG1223: 6 | AH1223: 0 | AI1223: 0 | AJ1223: 0
... A1358: 255-9010982 | B1358: =VLOOKUP(A1358,Sheet3!A:B,2,0) -> INV-205-2974 | C1358: Invoice | D1358: 21086 | E1358: GAMESA BARRAS DE COCO 106G | F1358: GAMESA | G1358: GALLETAS | H1358: GALLETAS DULCES | I1358: ------ | J1358: ------ | K1358: 10444 | L1358: Chevron #355144 | M1358: 255 - Carlos Morales | N1358: 205 | O1358: Carlos Morales | P1358: Sunmex Truck - 159 | Q1358: 105 | R1358: 02/17/2026 | S1358: 02 | T1358: 2026 | U1358: 5 | V1358: 5 | W1358: UNIT(S) | X1358: 2.09 | Y1358: 1.35 | Z1358: 0 | AA1358: 10.45 | AB1358: 35.41% | AC1358: 0 | AD1358: 0 | AE1358: 0 | AF1358: 0 | AG1358: 5 | AH1358: 0 | AI1358: 0 | AJ1358: 0
A1359: 259-9000560 | B1359: =VLOOKUP(A1359,Sheet3!A:B,2,0) -> INV-001-3055 | C1359: Invoice | D1359: 67674 | E1359: SAB RUFFLE QUESO 120G | F1359: SABRITAS | G1359: BOTANAS | H1359: MAIZ | I1359: CON QUESO | J1359: CON SABOR | K1359: 11719 | L1359: NC Distributor LLC. | M1359: 259 - Venta Administrativa | N1359: 001 | O1359: Ventas Administrativas | P1359: Sunmex Truck - 152 | Q1359: 001 | R1359: 02/17/2026 | S1359: 02 | T1359: 2026 | U1359: 840 | V1359: 840 | W1359: UNIT(S) | X1359: 2.1 | Y1359: 1.99 | Z1359: 0 | AA1359: 1764 | AB1359: 38.1% | AC1359: 579.6 | AD1359: 0 | AE1359: 0 | AF1359: 0 | AG1359: 840 | AH1359: 0 | AI1359: 0 | AJ1359: 0
A1360: 255-9010982 | B1360: =VLOOKUP(A1360,Sheet3!A:B,2,0) -> INV-205-2974 | C1360: Invoice | D1360: 16216 | E1360: PARR COKIE STRAWBERRY SAND/24CT | F1360: PARROT | G1360: GALLETAS | H1360: GALLETAS DULCES | I1360: CON SABOR | J1360: GALLETAS | K1360: 10444 | L1360: Chevron #355144 | M1360: 255 - Carlos Morales | N1360: 205 | O1360: Carlos Morales | P1360: Sunmex Truck - 159 | Q1360: 105 | R1360: 02/17/2026 | S1360: 02 | T1360: 2026 | U1360: 6 | V1360: 6 | W1360: UNIT(S) | X1360: 1.73 | Y1360: 1.07083 | Z1360: 0 | AA1360: 10.38 | AB1360: 38.1% | AC1360: 0 | AD1360: 0 | AE1360: 0 | AF1360: 0 | AG1360: 6 | AH1360: 0 | AI1360: 0 | AJ1360: 0
A1361: 255-9010982 | B1361: =VLOOKUP(A1361,Sheet3!A:B,2,0) -> INV-205-2974 | C1361: Invoice | D1361: 16220 | E1361: PARR COKIE PINK GUAVA SAND/24CT | F1361: PARROT | G1361: GALLETAS | H1361: GALLETAS DULCES | I1361: CON SABOR | J1361: GALLETAS | K1361: 10444 | L1361: Chevron #355144 | M1361: 255 - Carlos Morales | N1361: 205 | O1361: Carlos Morales | P1361: Sunmex Truck - 159 | Q1361: 105 | R1361: 02/17/2026 | S1361: 02 | T1361: 2026 | U1361: 3 | V1361: 5 | W1361: UNIT(S) | X1361: 1.73 | Y1361: 1.0208 | Z1361: 0 | AA1361: 8.65 | AB1361: 40.99% | AC1361: 0 | AD1361: 0 | AE1361: 0 | AF1361: 0 | AG1361: 5 | AH1361: 0 | AI1361: 0 | AJ1361: 0
A1362: 255-9010988 | B1362: =VLOOKUP(A1362,Sheet3!A:B,2,0) -> INV-205-2979 | C1362: Invoice | D1362: 24037 | E1362: PARR CAN MANGO 485ML/12CT | F1362: PARROT | G1362: BEBIDAS | H1362: JUGO DE FRUTAS | I1362: AGUA DE COCO | J1362: JUGO DE FRUTAS | K1362: 11144 | L1362: Quick Stop / Mcdowell | M1362: 255 - Carlos Morales | N1362: 205 | O1362: Carlos Morales | P1362: Sunmex Truck - 159 | Q1362: 105 | R1362: 02/17/2026 | S1362: 02 | T1362: 2026 | U1362: 12 | V1362: 12 | W1362: UNIT(S) | X1362: 1.583 | Y1362: 0.94583 | Z1362: 0 | AA1362: 18.996 | AB1362: 40.25% | AC1362: 0 | AD1362: 0 | AE1362: 0 | AF1362: 0 | AG1362: 12 | AH1362: 0 | AI1362: 0 | AJ1362: 0
A1363: 255-9010987 | B1363: =VLOOKUP(A1363,Sheet3!A:B,2,0) -> INV-205-2978 | C1363: Invoice | D1363: 30937 | E1363: SAB CHETO FLAMIN HOT 145G | F1363: SABRITAS | G1363: BOTANAS | H1363: MAIZ | I1363: CON QUESO | J1363: CON CHILE | K1363: 11649 | L1363: Neveria Los Tios | M1363: 255 - Carlos Morales | N1363: 205 | O1363: Carlos Morales | P1363: Sunmex Truck - 159 | Q1363: 105 | R1363: 02/17/2026 | S1363: 02 | T1363: 2026 | U1363: 20 | V1363: 20 | W1363: UNIT(S) | X1363: 2.49 | Y1363: 1.99 | Z1363: 0 | AA1363: 49.8 | AB1363: 32.13% | AC1363: 6 | AD1363: 0 | AE1363: 0 | AF1363: 0 | AG1363: 20 | AH1363: 0 | AI1363: 0 | AJ1363: 0
A1364: 255-9010987 | B1364: =VLOOKUP(A1364,Sheet3!A:B,2,0) -> INV-205-2978 | C1364: Invoice | D1364: 30920 | E1364: SAB CHETO BOLITAS 110G | F1364: SABRITAS | G1364: BOTANAS | H1364: MAIZ | I1364: CON QUESO | J1364: CON CHILE | K1364: 11649 | L1364: Neveria Los Tios | M1364: 255 - Carlos Morales | N1364: 205 | O1364: Carlos Morales | P1364: Sunmex Truck - 159 | Q1364: 105 | R1364: 02/17/2026 | S1364: 02 | T1364: 2026 | U1364: 15 | V1364: 15 | W1364: UNIT(S) | X1364: 2.49 | Y1364: 1.99 | Z1364: 0 | AA1364: 37.35 | AB1364: 32.13% | AC1364: 4.5 | AD1364: 0 | AE1364: 0 | AF1364: 0 | AG1364: 15 | AH1364: 0 | AI1364: 0 | AJ1364: 0
A1365: 255-9010987 | B1365: =VLOOKUP(A1365,Sheet3!A:B,2,0) -> INV-205-2978 | C1365: Invoice | D1365: 42296 | E1365: SAB CHURRUM FLAMIN HT 185G | F1365: SABRITAS | G1365: BOTANAS | H1365: MAIZ | I1365: CON CHILE | J1365: ------ | K1365: 11649 | L1365: Neveria Los Tios | M1365: 255 - Carlos Morales | N1365: 205 | O1365: Carlos Morales | P1365: Sunmex Truck - 159 | Q1365: 105 | R1365: 02/17/2026 | S1365: 02 | T1365: 2026 | U1365: 15 | V1365: 15 | W1365: UNIT(S) | X1365: 2.49 | Y1365: 1.99 | Z1365: 0 | AA1365: 37.35 | AB1365: 32.13% | AC1365: 4.5 | AD1365: 0 | AE1365: 0 | AF1365: 0 | AG1365: 15 | AH1365: 0 | AI1365: 0 | AJ1365: 0
A1366: 255-9010985 | B1366: =VLOOKUP(A1366,Sheet3!A:B,2,0) -> INV-205-2977 | C1366: Invoice | D1366: 67674 | E1366: SAB RUFFLE QUESO 120G | F1366: SABRITAS | G1366: BOTANAS | H1366: MAIZ | I1366: CON QUESO | J1366: CON SABOR | K1366: 10674 | L1366: Food City #143 | M1366: 255 - Carlos Morales | N1366: 205 | O1366: Carlos Morales | P1366: Sunmex Truck - 159 | Q1366: 105 | R1366: 02/17/2026 | S1366: 02 | T1366: 2026 | U1366: 10 | V1366: 10 | W1366: UNIT(S) | X1366: 2.99 | Y1366: 1.99 | Z1366: 0 | AA1366: 29.9 | AB1366: 26.76% | AC1366: -2 | AD1366: 0 | AE1366: 0 | AF1366: 0 | AG1366: 10 | AH1366: 0 | AI1366: 0 | AJ1366: 0
A1367: 255-9010985 | B1367: =VLOOKUP(A1367,Sheet3!A:B,2,0) -> INV-205-2977 | C1367: Invoice | D1367: 30869 | E1367: SAB TOSTITO SALSA 175G | F1367: SABRITAS | G1367: BOTANAS | H1367: MAIZ | I1367: CON SALSA VERDE | J1367: CON SABOR | K1367: 10674 | L1367: Food City #143 | M1367: 255 - Carlos Morales | N1367: 205 | O1367: Carlos Morales | P1367: Sunmex Truck - 159 | Q1367: 105 | R1367: 02/17/2026 | S1367: 02 | T1367: 2026 | U1367: 10 | V1367: 10 | W1367: UNIT(S) | X1367: 2.99 | Y1367: 1.99 | Z1367: 0 | AA1367: 29.9 | AB1367: 26.76% | AC1367: -2 | AD1367: 0 | AE1367: 0 | AF1367: 0 | AG1367: 10 | AH1367: 0 | AI1367: 0 | AJ1367: 0
A1368: 255-9010985 | B1368: =VLOOKUP(A1368,Sheet3!A:B,2,0) -> INV-205-2977 | C1368: Invoice | D1368: 42296 | E1368: SAB CHURRUM FLAMIN HT 185G | F1368: SABRITAS | G1368: BOTANAS | H1368: MAIZ | I1368: CON CHILE | J1368: ------ | K1368: 10674 | L1368: Food City #143 | M1368: 255 - Carlos Morales | N1368: 205 | O1368: Carlos Morales | P1368: Sunmex Truck - 159 | Q1368: 105 | R1368: 02/17/2026 | S1368: 02 | T1368: 2026 | U1368: 5 | V1368: 5 | W1368: UNIT(S) | X1368: 2.99 | Y1368: 1.99 | Z1368: 0 | AA1368: 14.95 | AB1368: 26.76% | AC1368: -1 | AD1368: 0 | AE1368: 0 | AF1368: 0 | AG1368: 5 | AH1368: 0 | AI1368: 0 | AJ1368: 0
A1369: 255-9010985 | B1369: =VLOOKUP(A1369,Sheet3!A:B,2,0) -> INV-205-2977 | C1369: Invoice | D1369: 12559 | E1369: SAB CHURRUM LIMON 185G | F1369: SABRITAS | G1369: BOTANAS | H1369: MAIZ | I1369: CON CHILE | J1369: CON LIMON | K1369: 10674 | L1369: Food City #143 | M1369: 255 - Carlos Morales | N1369: 205 | O1369: Carlos Morales | P1369: Sunmex Truck - 159 | Q1369: 105 | R1369: 02/17/2026 | S1369: 02 | T1369: 2026 | U1369: 5 | V1369: 5 | W1369: UNIT(S) | X1369: 2.99 | Y1369: 1.99 | Z1369: 0 | AA1369: 14.95 | AB1369: 26.76% | AC1369: -1 | AD1369: 0 | AE1369: 0 | AF1369: 0 | AG1369: 5 | AH1369: 0 | AI1369: 0 | AJ1369: 0
A1370: 255-9010985 | B1370: =VLOOKUP(A1370,Sheet3!A:B,2,0) -> INV-205-2977 | C1370: Invoice | D1370: 31064 | E1370: SAB DORITO NACHOS 146G | F1370: SABRITAS | G1370: BOTANAS | H1370: MAIZ | I1370: CON QUESO | J1370: CON CHILE | K1370: 10674 | L1370: Food City #143 | M1370: 255 - Carlos Morales | N1370: 205 | O1370: Carlos Morales | P1370: Sunmex Truck - 159 | Q1370: 105 | R1370: 02/17/2026 | S1370: 02 | T1370: 2026 | U1370: 5 | V1370: 5 | W1370: UNIT(S) | X1370: 2.99 | Y1370: 1.99 | Z1370: 0 | AA1370: 14.95 | AB1370: 26.76% | AC1370: -1 | AD1370: 0 | AE1370: 0 | AF1370: 0 | AG1370: 5 | AH1370: 0 | AI1370: 0 | AJ1370: 0
A1371: 255-9010985 | B1371: =VLOOKUP(A1371,Sheet3!A:B,2,0) -> INV-205-2977 | C1371: Invoice | D1371: 14517 | E1371: SAB RANCHERITOS 145G | F1371: SABRITAS | G1371: BOTANAS | H1371: MAIZ | I1371: CON CHILE | J1371: CON SABOR | K1371: 10674 | L1371: Food City #143 | M1371: 255 - Carlos Morales | N1371: 205 | O1371: Carlos Morales | P1371: Sunmex Truck - 159 | Q1371: 105 | R1371: 02/17/2026 | S1371: 02 | T1371: 2026 | U1371: 5 | V1371: 5 | W1371: UNIT(S) | X1371: 2.99 | Y1371: 1.99 | Z1371: 0 | AA1371: 14.95 | AB1371: 26.76% | AC1371: -1 | AD1371: 0 | AE1371: 0 | AF1371: 0 | AG1371: 5 | AH1371: 0 | AI1371: 0 | AJ1371: 0
... A2005: 256-9009429 | B2005: =VLOOKUP(A2005,Sheet3!A:B,2,0) -> INV-206-3020 | C2005: Invoice | D2005: 30937 | E2005: SAB CHETO FLAMIN HOT 145G | F2005: SABRITAS | G2005: BOTANAS | H2005: MAIZ | I2005: CON QUESO | J2005: CON CHILE | K2005: 10103 | L2005: A B Check Cashing | M2005: 256 - Ana Ibarra | N2005: 206 | O2005: Ana Ibarra | P2005: Sunmex Truck - 156 | Q2005: 104 | R2005: 02/17/2026 | S2005: 02 | T2005: 2026 | U2005: 10 | V2005: 10 | W2005: UNIT(S) | X2005: 2.79 | Y2005: 1.99 | Z2005: 0 | AA2005: 27.9 | AB2005: 28.67% | AC2005: 0 | AD2005: 0 | AE2005: 0 | AF2005: 0 | AG2005: 10 | AH2005: 0 | AI2005: 0 | AJ2005: 0
A2006: 259-9000560 | B2006: =VLOOKUP(A2006,Sheet3!A:B,2,0) -> INV-001-3055 | C2006: Invoice | D2006: 14517 | E2006: SAB RANCHERITOS 145G | F2006: SABRITAS | G2006: BOTANAS | H2006: MAIZ | I2006: CON CHILE | J2006: CON SABOR | K2006: 11719 | L2006: NC Distributor LLC. | M2006: 259 - Venta Administrativa | N2006: 001 | O2006: Ventas Administrativas | P2006: Sunmex Truck - 152 | Q2006: 001 | R2006: 02/17/2026 | S2006: 02 | T2006: 2026 | U2006: 480 | V2006: 480 | W2006: UNIT(S) | X2006: 2.1 | Y2006: 1.99 | Z2006: 0 | AA2006: 1008 | AB2006: 38.1% | AC2006: 331.2 | AD2006: 0 | AE2006: 0 | AF2006: 0 | AG2006: 480 | AH2006: 0 | AI2006: 0 | AJ2006: 0
A2007: 255-9010985 | B2007: =VLOOKUP(A2007,Sheet3!A:B,2,0) -> INV-205-2977 | C2007: Invoice | D2007: 30876 | E2007: SAB TOSTITO FLAMIN H 175G | F2007: SABRITAS | G2007: BOTANAS | H2007: MAIZ | I2007: CON CHILE | J2007: CON SABOR | K2007: 10674 | L2007: Food City #143 | M2007: 255 - Carlos Morales | N2007: 205 | O2007: Carlos Morales | P2007: Sunmex Truck - 159 | Q2007: 105 | R2007: 02/17/2026 | S2007: 02 | T2007: 2026 | U2007: 10 | V2007: 10 | W2007: UNIT(S) | X2007: 2.99 | Y2007: 1.99 | Z2007: 0 | AA2007: 29.9 | AB2007: 26.76% | AC2007: -2 | AD2007: 0 | AE2007: 0 | AF2007: 0 | AG2007: 10 | AH2007: 0 | AI2007: 0 | AJ2007: 0
A2008: 354-9001489 | B2008: =VLOOKUP(A2008,Sheet3!A:B,2,0) -> INV-251-3074 | C2008: Invoice | D2008: 67667 | E2008: SAB PAPA ADOBADA 105G | F2008: SABRITAS | G2008: BOTANAS | H2008: PAPAS | I2008: CON ADOBO | J2008: CON SABOR | K2008: 10648 | L2008: Food City #060 | M2008: 354 - Joa Ibarra | N2008: 251 | O2008: Joa Ibarra | P2008: Sunmex Truck - 351 | Q2008: 102 | R2008: 02/17/2026 | S2008: 02 | T2008: 2026 | U2008: 20 | V2008: 20 | W2008: UNIT(S) | X2008: 2.99 | Y2008: 1.99 | Z2008: 0 | AA2008: 59.8 | AB2008: 26.76% | AC2008: -4 | AD2008: 0 | AE2008: 0 | AF2008: 0 | AG2008: 20 | AH2008: 0 | AI2008: 0 | AJ2008: 0
A2009: 256-9009436 | B2009: =VLOOKUP(A2009,Sheet3!A:B,2,0) -> INV-206-3025 | C2009: Invoice | D2009: 54902 | E2009: SAB PAKETAXO AMARILLO 265G | F2009: SABRITAS | G2009: BOTANAS | H2009: ------ | I2009: ------ | J2009: ------ | K2009: 10599 | L2009: El Rancho Barajas LLC | M2009: 256 - Ana Ibarra | N2009: 206 | O2009: Ana Ibarra | P2009: Sunmex Truck - 156 | Q2009: 104 | R2009: 02/17/2026 | S2009: 02 | T2009: 2026 | U2009: 10 | V2009: 12 | W2009: UNIT(S) | X2009: 4.29 | Y2009: 3.05 | Z2009: 0 | AA2009: 51.48 | AB2009: 28.9% | AC2009: 0 | AD2009: 0 | AE2009: 0 | AF2009: 0 | AG2009: 12 | AH2009: 0 | AI2009: 0 | AJ2009: 0
A2010: 354-9001488 | B2010: =VLOOKUP(A2010,Sheet3!A:B,2,0) -> INV-251-3073 | C2010: Invoice | D2010: 13907 | E2010: DIANDI COYOTA DUL LECH 9.52/14CT | F2010: DIANDI | G2010: PANES | H2010: COYOTAS | I2010: RELLENOS | J2010: DULCE DE LECHE | K2010: 10661 | L2010: Food City #111 | M2010: 354 - Joa Ibarra | N2010: 251 | O2010: Joa Ibarra | P2010: Sunmex Truck - 351 | Q2010: 102 | R2010: 02/17/2026 | S2010: 02 | T2010: 2026 | U2010: 14 | V2010: 14 | W2010: UNIT(S) | X2010: 2.35 | Y2010: 1.68 | Z2010: 0 | AA2010: 32.9 | AB2010: 36.17% | AC2010: 2.52 | AD2010: 0 | AE2010: 0 | AF2010: 0 | AG2010: 14 | AH2010: 0 | AI2010: 0 | AJ2010: 0
A2011: 253-9015803 | B2011: =VLOOKUP(A2011,Sheet3!A:B,2,0) -> INV-203-2870 | C2011: Invoice | D2011: 27542 | E2011: DE LA JAPON NISHIYAMA 170G/12CT | F2011: DE LA ROSA | G2011: BOTANAS | H2011: ------ | I2011: ------ | J2011: ------ | K2011: 11006 | L2011: Pull N Save Glendale | M2011: 253 - Balbina Rodriguez | N2011: 203 | O2011: Balbina Rodriguez | P2011: Sunmex Truck - 161 | Q2011: 106 | R2011: 02/17/2026 | S2011: 02 | T2011: 2026 | U2011: 1 | V2011: 1 | W2011: UNIT(S) | X2011: 6.99 | Y2011: 4.625 | Z2011: 0 | AA2011: 6.99 | AB2011: 33.83% | AC2011: 0 | AD2011: 0 | AE2011: 0 | AF2011: 0 | AG2011: 1 | AH2011: 0 | AI2011: 0 | AJ2011: 0
A2012: 256-9009430 | B2012: =VLOOKUP(A2012,Sheet3!A:B,2,0) -> INV-206-3021 | C2012: Invoice | D2012: 67667 | E2012: SAB PAPA ADOBADA 105G | F2012: SABRITAS | G2012: BOTANAS | H2012: PAPAS | I2012: CON ADOBO | J2012: CON SABOR | K2012: 10322 | L2012: Carioca #88 | M2012: 256 - Ana Ibarra | N2012: 206 | O2012: Ana Ibarra | P2012: Sunmex Truck - 156 | Q2012: 104 | R2012: 02/17/2026 | S2012: 02 | T2012: 2026 | U2012: 5 | V2012: 5 | W2012: UNIT(S) | X2012: 2.79 | Y2012: 1.99 | Z2012: 0 | AA2012: 13.95 | AB2012: 28.67% | AC2012: 0 | AD2012: 0 | AE2012: 0 | AF2012: 0 | AG2012: 5 | AH2012: 0 | AI2012: 0 | AJ2012: 0
A2013: 255-9010980 | B2013: =VLOOKUP(A2013,Sheet3!A:B,2,0) -> INV-205-2972 | C2013: Invoice | D2013: 12559 | E2013: SAB CHURRUM LIMON 185G | F2013: SABRITAS | G2013: BOTANAS | H2013: MAIZ | I2013: CON CHILE | J2013: CON LIMON | K2013: 10168 | L2013: Arco / Mini Mart | M2013: 255 - Carlos Morales | N2013: 205 | O2013: Carlos Morales | P2013: Sunmex Truck - 159 | Q2013: 105 | R2013: 02/17/2026 | S2013: 02 | T2013: 2026 | U2013: 5 | V2013: 5 | W2013: UNIT(S) | X2013: 2.79 | Y2013: 1.99 | Z2013: 0 | AA2013: 13.95 | AB2013: 28.67% | AC2013: 0 | AD2013: 0 | AE2013: 0 | AF2013: 0 | AG2013: 5 | AH2013: 0 | AI2013: 0 | AJ2013: 0
A2014: 253-9015797 | B2014: =VLOOKUP(A2014,Sheet3!A:B,2,0) -> INV-203-2865 | C2014: Invoice | D2014: 57790 | E2014: COCA COLA GLASS 500ML/24CT | F2014: COCA COLA | G2014: BEBIDAS | H2014: BEBIDA CON SABOR | I2014: BEBIDA CON GAS | J2014: BEBIDA CON GAS | K2014: 10652 | L2014: Food City #089 | M2014: 253 - Balbina Rodriguez | N2014: 203 | O2014: Balbina Rodriguez | P2014: Sunmex Truck - 161 | Q2014: 106 | R2014: 02/17/2026 | S2014: 02 | T2014: 2026 | U2014: 24 | V2014: 24 | W2014: UNIT(S) | X2014: 1.79 | Y2014: 1.55 | Z2014: 0 | AA2014: 42.96 | AB2014: 11.17% | AC2014: -0.96 | AD2014: 0 | AE2014: 0 | AF2014: 0 | AG2014: 24 | AH2014: 0 | AI2014: 0 | AJ2014: 0
A2015: 354-9001487 | B2015: =VLOOKUP(A2015,Sheet3!A:B,2,0) -> INV-251-3072 | C2015: Invoice | D2015: 30876 | E2015: SAB TOSTITO FLAMIN H 175G | F2015: SABRITAS | G2015: BOTANAS | H2015: MAIZ | I2015: CON CHILE | J2015: CON SABOR | K2015: 10661 | L2015: Food City #111 | M2015: 354 - Joa Ibarra | N2015: 251 | O2015: Joa Ibarra | P2015: Sunmex Truck - 351 | Q2015: 102 | R2015: 02/17/2026 | S2015: 02 | T2015: 2026 | U2015: 20 | V2015: 20 | W2015: UNIT(S) | X2015: 2.99 | Y2015: 1.99 | Z2015: 0 | AA2015: 59.8 | AB2015: 26.76% | AC2015: -4 | AD2015: 0 | AE2015: 0 | AF2015: 0 | AG2015: 20 | AH2015: 0 | AI2015: 0 | AJ2015: 0
A2016: 254-9011987 | B2016: =VLOOKUP(A2016,Sheet3!A:B,2,0) -> INV-204-2924 | C2016: Invoice | D2016: 74069 | E2016: JUMEX GLASS GUAVA 413ML/12CT | F2016: JUMEX GLASS | G2016: BEBIDAS | H2016: JUGO DE FRUTAS | I2016: JUGO DE FRUTAS | J2016: JUGO DE FRUTAS | K2016: 11526 | L2016: Grab and Go Convenience Market | M2016: 254 - Yurithzin Perez | N2016: 204 | O2016: Yurithzin Perez | P2016: Sunmex Truck - 151 | Q2016: 101 | R2016: 02/17/2026 | S2016: 02 | T2016: 2026 | U2016: 12 | V2016: 12 | W2016: UNIT(S) | X2016: 1.39 | Y2016: 1.11 | Z2016: 0 | AA2016: 16.68 | AB2016: 20.14% | AC2016: 0 | AD2016: 0 | AE2016: 0 | AF2016: 0 | AG2016: 12 | AH2016: 0 | AI2016: 0 | AJ2016: 0
A2017: 256-9009436 | B2017: =VLOOKUP(A2017,Sheet3!A:B,2,0) -> INV-206-3025 | C2017: Invoice | D2017: 13700 | E2017: PEPSI COLA GLASS 500ML/24CT | F2017: PEPSI | G2017: BEBIDAS | H2017: ------ | I2017: ------ | J2017: ------ | K2017: 10599 | L2017: El Rancho Barajas LLC | M2017: 256 - Ana Ibarra | N2017: 206 | O2017: Ana Ibarra | P2017: Sunmex Truck - 156 | Q2017: 104 | R2017: 02/17/2026 | S2017: 02 | T2017: 2026 | U2017: 24 | V2017: 24 | W2017: UNIT(S) | X2017: 1.833 | Y2017: 1.55 | Z2017: 0 | AA2017: 43.992 | AB2017: 15.44% | AC2017: 0 | AD2017: 0 | AE2017: 0 | AF2017: 0 | AG2017: 24 | AH2017: 0 | AI2017: 0 | AJ2017: 0
A2018: 256-9009430 | B2018: =VLOOKUP(A2018,Sheet3!A:B,2,0) -> INV-206-3021 | C2018: Invoice | D2018: 55022 | E2018: SAB PAKETAXO MORADO 215G | F2018: SABRITAS | G2018: BOTANAS | H2018: PAPAS | I2018: ------ | J2018: ------ | K2018: 10322 | L2018: Carioca #88 | M2018: 256 - Ana Ibarra | N2018: 206 | O2018: Ana Ibarra | P2018: Sunmex Truck - 156 | Q2018: 104 | R2018: 02/17/2026 | S2018: 02 | T2018: 2026 | U2018: 5 | V2018: 5 | W2018: UNIT(S) | X2018: 4.49 | Y2018: 3.05 | Z2018: 0 | AA2018: 22.45 | AB2018: 27.62% | AC2018: -1 | AD2018: 0 | AE2018: 0 | AF2018: 0 | AG2018: 5 | AH2018: 0 | AI2018: 0 | AJ2018: 0
... A2123: 256-9009433 | B2123: =VLOOKUP(A2123,Sheet3!A:B,2,0) -> INV-206-3023 | C2123: Invoice | D2123: 14879 | E2123: DE LA MAZAPAN CHOCO GIANT/16CT | F2123: DE LA ROSA | G2123: DULCES | H2123: MAZAPANES | I2123: MAZAPANES | J2123: MAZAPANES | K2123: 11716 | L2123: Carniceria Sonora #4 | M2123: 256 - Ana Ibarra | N2123: 206 | O2123: Ana Ibarra | P2123: Sunmex Truck - 156 | Q2123: 104 | R2123: 02/17/2026 | S2123: 02 | T2123: 2026 | U2123: 1 | V2123: 1 | W2123: UNIT(S) | X2123: 7.82 | Y2123: 5.625 | Z2123: 0 | AA2123: 7.82 | AB2123: 39.19% | AC2123: 0.87 | AD2123: 0 | AE2123: 0 | AF2123: 0 | AG2123: 1 | AH2123: 0 | AI2123: 0 | AJ2123: 0
A2124: 259-9000560 | B2124: =VLOOKUP(A2124,Sheet3!A:B,2,0) -> INV-001-3055 | C2124: Invoice | D2124: 31040 | E2124: SAB CRUJITOS QUESO 120G | F2124: SABRITAS | G2124: BOTANAS | H2124: MAIZ | I2124: CON QUESO | J2124: CON CHILE | K2124: 11719 | L2124: NC Distributor LLC. | M2124: 259 - Venta Administrativa | N2124: 001 | O2124: Ventas Administrativas | P2124: Sunmex Truck - 152 | Q2124: 001 | R2124: 02/17/2026 | S2124: 02 | T2124: 2026 | U2124: 84 | V2124: 84 | W2124: UNIT(S) | X2124: 2.1 | Y2124: 1.99 | Z2124: 0 | AA2124: 176.4 | AB2124: 38.1% | AC2124: 57.96 | AD2124: 0 | AE2124: 0 | AF2124: 0 | AG2124: 84 | AH2124: 0 | AI2124: 0 | AJ2124: 0
A2125: 256-9009432 | B2125: =VLOOKUP(A2125,Sheet3!A:B,2,0) -> INV-206-3022 | C2125: Invoice | D2125: 30876 | E2125: SAB TOSTITO FLAMIN H 175G | F2125: SABRITAS | G2125: BOTANAS | H2125: MAIZ | I2125: CON CHILE | J2125: CON SABOR | K2125: 11716 | L2125: Carniceria Sonora #4 | M2125: 256 - Ana Ibarra | N2125: 206 | O2125: Ana Ibarra | P2125: Sunmex Truck - 156 | Q2125: 104 | R2125: 02/17/2026 | S2125: 02 | T2125: 2026 | U2125: 50 | V2125: 60 | W2125: UNIT(S) | X2125: 2.39 | Y2125: 1.99 | Z2125: 0 | AA2125: 143.4 | AB2125: 33.47% | AC2125: 24 | AD2125: 0 | AE2125: 0 | AF2125: 0 | AG2125: 60 | AH2125: 0 | AI2125: 0 | AJ2125: 0
A2126: 256-9009436 | B2126: =VLOOKUP(A2126,Sheet3!A:B,2,0) -> INV-206-3025 | C2126: Invoice | D2126: 31125 | E2126: SAB FRITO LIMON SAL 170G | F2126: SABRITAS | G2126: BOTANAS | H2126: MAIZ | I2126: CON SAL | J2126: CON LIMON | K2126: 10599 | L2126: El Rancho Barajas LLC | M2126: 256 - Ana Ibarra | N2126: 206 | O2126: Ana Ibarra | P2126: Sunmex Truck - 156 | Q2126: 104 | R2126: 02/17/2026 | S2126: 02 | T2126: 2026 | U2126: 10 | V2126: 10 | W2126: UNIT(S) | X2126: 2.59 | Y2126: 1.99 | Z2126: 0 | AA2126: 25.9 | AB2126: 30.89% | AC2126: 2 | AD2126: 0 | AE2126: 0 | AF2126: 0 | AG2126: 10 | AH2126: 0 | AI2126: 0 | AJ2126: 0
A2127: 254-9011984 | B2127: =VLOOKUP(A2127,Sheet3!A:B,2,0) -> INV-204-2922 | C2127: Invoice | D2127: 30869 | E2127: SAB TOSTITO SALSA 175G | F2127: SABRITAS | G2127: BOTANAS | H2127: MAIZ | I2127: CON SALSA VERDE | J2127: CON SABOR | K2127: 10647 | L2127: Food City #041 | M2127: 254 - Yurithzin Perez | N2127: 204 | O2127: Yurithzin Perez | P2127: Sunmex Truck - 151 | Q2127: 101 | R2127: 02/17/2026 | S2127: 02 | T2127: 2026 | U2127: 20 | V2127: 20 | W2127: UNIT(S) | X2127: 2.99 | Y2127: 1.99 | Z2127: 0 | AA2127: 59.8 | AB2127: 26.76% | AC2127: -4 | AD2127: 0 | AE2127: 0 | AF2127: 0 | AG2127: 20 | AH2127: 0 | AI2127: 0 | AJ2127: 0
A2128: 255-9010978 | B2128: =VLOOKUP(A2128,Sheet3!A:B,2,0) -> INV-205-2970 | C2128: Invoice | D2128: 30937 | E2128: SAB CHETO FLAMIN HOT 145G | F2128: SABRITAS | G2128: BOTANAS | H2128: MAIZ | I2128: CON QUESO | J2128: CON CHILE | K2128: 11829 | L2128: Chevron Extra Mile / 7th St | M2128: 255 - Carlos Morales | N2128: 205 | O2128: Carlos Morales | P2128: Sunmex Truck - 151 | Q2128: 101 | R2128: 02/17/2026 | S2128: 02 | T2128: 2026 | U2128: 20 | V2128: 20 | W2128: UNIT(S) | X2128: 2.79 | Y2128: 1.99 | Z2128: 0 | AA2128: 55.8 | AB2128: 28.67% | AC2128: 0 | AD2128: 0 | AE2128: 0 | AF2128: 0 | AG2128: 20 | AH2128: 0 | AI2128: 0 | AJ2128: 0
A2129: 254-9011984 | B2129: =VLOOKUP(A2129,Sheet3!A:B,2,0) -> INV-204-2922 | C2129: Invoice | D2129: 13359 | E2129: JUMEX GLASS DURAZNO 413ML/12CT | F2129: JUMEX GLASS | G2129: BEBIDAS | H2129: JUGO DE FRUTAS | I2129: JUGO DE FRUTAS | J2129: JUGO DE FRUTAS | K2129: 10647 | L2129: Food City #041 | M2129: 254 - Yurithzin Perez | N2129: 204 | O2129: Yurithzin Perez | P2129: Sunmex Truck - 151 | Q2129: 101 | R2129: 02/17/2026 | S2129: 02 | T2129: 2026 | U2129: 24 | V2129: 24 | W2129: UNIT(S) | X2129: 1.29 | Y2129: 1.11 | Z2129: 0 | AA2129: 30.96 | AB2129: 21.71% | AC2129: 2.4 | AD2129: 0 | AE2129: 0 | AF2129: 0 | AG2129: 24 | AH2129: 0 | AI2129: 0 | AJ2129: 0
A2130: 254-9011983 | B2130: =VLOOKUP(A2130,Sheet3!A:B,2,0) -> INV-204-2921 | C2130: Invoice | D2130: 12559 | E2130: SAB CHURRUM LIMON 185G | F2130: SABRITAS | G2130: BOTANAS | H2130: MAIZ | I2130: CON CHILE | J2130: CON LIMON | K2130: 11827 | L2130: Food and Things Liquor & Deli | M2130: 254 - Yurithzin Perez | N2130: 204 | O2130: Yurithzin Perez | P2130: Sunmex Truck - 151 | Q2130: 101 | R2130: 02/17/2026 | S2130: 02 | T2130: 2026 | U2130: 5 | V2130: 5 | W2130: UNIT(S) | X2130: 2.79 | Y2130: 1.99 | Z2130: 0 | AA2130: 13.95 | AB2130: 28.67% | AC2130: 0 | AD2130: 0 | AE2130: 0 | AF2130: 0 | AG2130: 5 | AH2130: 0 | AI2130: 0 | AJ2130: 0
A2131: 255-9010991 | B2131: =VLOOKUP(A2131,Sheet3!A:B,2,0) -> INV-205-2982 | C2131: Invoice | D2131: 30937 | E2131: SAB CHETO FLAMIN HOT 145G | F2131: SABRITAS | G2131: BOTANAS | H2131: MAIZ | I2131: CON QUESO | J2131: CON CHILE | K2131: 11398 | L2131: Walgreens #03789 | M2131: 255 - Carlos Morales | N2131: 205 | O2131: Carlos Morales | P2131: Sunmex Truck - 159 | Q2131: 105 | R2131: 02/17/2026 | S2131: 02 | T2131: 2026 | U2131: 5 | V2131: 5 | W2131: UNIT(S) | X2131: 2.99 | Y2131: 1.99 | Z2131: 0 | AA2131: 14.95 | AB2131: 26.76% | AC2131: -1 | AD2131: 0 | AE2131: 0 | AF2131: 0 | AG2131: 5 | AH2131: 0 | AI2131: 0 | AJ2131: 0
A2132: 255-9010980 | B2132: =VLOOKUP(A2132,Sheet3!A:B,2,0) -> INV-205-2972 | C2132: Invoice | D2132: 66234 | E2132: BARCEL CHIP JALAPENO 170G | F2132: BARCEL | G2132: BOTANAS | H2132: PAPAS | I2132: CON SABOR | J2132: ------ | K2132: 10168 | L2132: Arco / Mini Mart | M2132: 255 - Carlos Morales | N2132: 205 | O2132: Carlos Morales | P2132: Sunmex Truck - 159 | Q2132: 105 | R2132: 02/17/2026 | S2132: 02 | T2132: 2026 | U2132: 5 | V2132: 5 | W2132: UNIT(S) | X2132: 5.19 | Y2132: 3.45 | Z2132: 0 | AA2132: 25.95 | AB2132: 33.53% | AC2132: 0 | AD2132: 0 | AE2132: 0 | AF2132: 0 | AG2132: 5 | AH2132: 0 | AI2132: 0 | AJ2132: 0
A2133: 256-9009433 | B2133: =VLOOKUP(A2133,Sheet3!A:B,2,0) -> INV-206-3023 | C2133: Invoice | D2133: 21269 | E2133: BARCEL RUNNER 200GR | F2133: BARCEL | G2133: BOTANAS | H2133: MAIZ | I2133: ------ | J2133: ------ | K2133: 11716 | L2133: Carniceria Sonora #4 | M2133: 256 - Ana Ibarra | N2133: 206 | O2133: Ana Ibarra | P2133: Sunmex Truck - 156 | Q2133: 104 | R2133: 02/17/2026 | S2133: 02 | T2133: 2026 | U2133: 10 | V2133: 10 | W2133: UNIT(S) | X2133: 3.69 | Y2133: 2.55 | Z2133: 0 | AA2133: 36.9 | AB2133: 36.31% | AC2133: 2 | AD2133: 0 | AE2133: 0 | AF2133: 0 | AG2133: 10 | AH2133: 0 | AI2133: 0 | AJ2133: 0
A2134: 253-9015800 | B2134: =VLOOKUP(A2134,Sheet3!A:B,2,0) -> INV-203-2868 | C2134: Invoice | D2134: 24000 | E2134: PARR GLASS BANANA COCO 290/12CT | F2134: PARROT | G2134: BEBIDAS | H2134: JUGO DE FRUTAS | I2134: AGUA DE COCO | J2134: CON LECHE DE COCO | K2134: 10383 | L2134: Carniceria Sonora / Washington | M2134: 253 - Balbina Rodriguez | N2134: 203 | O2134: Balbina Rodriguez | P2134: Sunmex Truck - 161 | Q2134: 106 | R2134: 02/17/2026 | S2134: 02 | T2134: 2026 | U2134: 12 | V2134: 12 | W2134: UNIT(S) | X2134: 1.89 | Y2134: 0.98755 | Z2134: 0 | AA2134: 22.68 | AB2134: 47.75% | AC2134: 0 | AD2134: 0 | AE2134: 0 | AF2134: 0 | AG2134: 12 | AH2134: 0 | AI2134: 0 | AJ2134: 0
A2135: 251-9012483 | B2135: =VLOOKUP(A2135,Sheet3!A:B,2,0) -> INV-201-2766 | C2135: Invoice | D2135: 42296 | E2135: SAB CHURRUM FLAMIN HT 185G | F2135: SABRITAS | G2135: BOTANAS | H2135: MAIZ | I2135: CON CHILE | J2135: ------ | K2135: 11185 | L2135: Saguaro Market | M2135: 251 - Manuel Ayala | N2135: 201 | O2135: Manuel Ayala | P2135: Sunmex Truck - 153 | Q2135: 103 | R2135: 02/17/2026 | S2135: 02 | T2135: 2026 | U2135: 5 | V2135: 5 | W2135: UNIT(S) | X2135: 2.79 | Y2135: 1.99 | Z2135: 0 | AA2135: 13.95 | AB2135: 28.67% | AC2135: 0 | AD2135: 0 | AE2135: 0 | AF2135: 0 | AG2135: 5 | AH2135: 0 | AI2135: 0 | AJ2135: 0
A2136: 251-9012483 | B2136: =VLOOKUP(A2136,Sheet3!A:B,2,0) -> INV-201-2766 | C2136: Invoice | D2136: 30869 | E2136: SAB TOSTITO SALSA 175G | F2136: SABRITAS | G2136: BOTANAS | H2136: MAIZ | I2136: CON SALSA VERDE | J2136: CON SABOR | K2136: 11185 | L2136: Saguaro Market | M2136: 251 - Manuel Ayala | N2136: 201 | O2136: Manuel Ayala | P2136: Sunmex Truck - 153 | Q2136: 103 | R2136: 02/17/2026 | S2136: 02 | T2136: 2026 | U2136: 25 | V2136: 25 | W2136: UNIT(S) | X2136: 2.79 | Y2136: 1.99 | Z2136: 0 | AA2136: 69.75 | AB2136: 28.67% | AC2136: 0 | AD2136: 0 | AE2136: 0 | AF2136: 0 | AG2136: 25 | AH2136: 0 | AI2136: 0 | AJ2136: 0
... A2286: 251-9012482 | B2286: =VLOOKUP(A2286,Sheet3!A:B,2,0) -> INV-201-2765 | C2286: Invoice | D2286: 30975 | E2286: SAB CHETO TORCIDITOS 145G | F2286: SABRITAS | G2286: BOTANAS | H2286: MAIZ | I2286: CON QUESO | J2286: CON CHILE | K2286: 11188 | L2286: Salome Market | M2286: 251 - Manuel Ayala | N2286: 201 | O2286: Manuel Ayala | P2286: Sunmex Truck - 153 | Q2286: 103 | R2286: 02/17/2026 | S2286: 02 | T2286: 2026 | U2286: 5 | V2286: 5 | W2286: UNIT(S) | X2286: 2.79 | Y2286: 1.99 | Z2286: 0 | AA2286: 13.95 | AB2286: 28.67% | AC2286: 0 | AD2286: 0 | AE2286: 0 | AF2286: 0 | AG2286: 5 | AH2286: 0 | AI2286: 0 | AJ2286: 0
A2287: 259-9000560 | B2287: =VLOOKUP(A2287,Sheet3!A:B,2,0) -> INV-001-3055 | C2287: Invoice | D2287: 30876 | E2287: SAB TOSTITO FLAMIN H 175G | F2287: SABRITAS | G2287: BOTANAS | H2287: MAIZ | I2287: CON CHILE | J2287: CON SABOR | K2287: 11719 | L2287: NC Distributor LLC. | M2287: 259 - Venta Administrativa | N2287: 001 | O2287: Ventas Administrativas | P2287: Sunmex Truck - 152 | Q2287: 001 | R2287: 02/17/2026 | S2287: 02 | T2287: 2026 | U2287: 390 | V2287: 390 | W2287: UNIT(S) | X2287: 2.1 | Y2287: 1.99 | Z2287: 0 | AA2287: 819 | AB2287: 38.1% | AC2287: 269.1 | AD2287: 0 | AE2287: 0 | AF2287: 0 | AG2287: 390 | AH2287: 0 | AI2287: 0 | AJ2287: 0
A2288: 253-9015803 | B2288: =VLOOKUP(A2288,Sheet3!A:B,2,0) -> INV-203-2870 | C2288: Invoice | D2288: 66860 | E2288: JUMEX CAN COCO-PINEAP 16OZ/12CT | F2288: JUMEX | G2288: BEBIDAS | H2288: JUGO DE FRUTAS | I2288: JUGO DE FRUTAS | J2288: JUGO DE FRUTAS | K2288: 11006 | L2288: Pull N Save Glendale | M2288: 253 - Balbina Rodriguez | N2288: 203 | O2288: Balbina Rodriguez | P2288: Sunmex Truck - 161 | Q2288: 106 | R2288: 02/17/2026 | S2288: 02 | T2288: 2026 | U2288: 12 | V2288: 12 | W2288: UNIT(S) | X2288: 1.59 | Y2288: 1.06 | Z2288: 0 | AA2288: 19.08 | AB2288: 33.33% | AC2288: 0 | AD2288: 0 | AE2288: 0 | AF2288: 0 | AG2288: 12 | AH2288: 0 | AI2288: 0 | AJ2288: 0
A2289: 253-9015801 | B2289: =VLOOKUP(A2289,Sheet3!A:B,2,0) -> INV-203-2869 | C2289: Invoice | D2289: 30920 | E2289: SAB CHETO BOLITAS 110G | F2289: SABRITAS | G2289: BOTANAS | H2289: MAIZ | I2289: CON QUESO | J2289: CON CHILE | K2289: 10482 | L2289: Country Market | M2289: 253 - Balbina Rodriguez | N2289: 203 | O2289: Balbina Rodriguez | P2289: Sunmex Truck - 161 | Q2289: 106 | R2289: 02/17/2026 | S2289: 02 | T2289: 2026 | U2289: 5 | V2289: 5 | W2289: UNIT(S) | X2289: 2.79 | Y2289: 1.99 | Z2289: 0 | AA2289: 13.95 | AB2289: 28.67% | AC2289: 0 | AD2289: 0 | AE2289: 0 | AF2289: 0 | AG2289: 5 | AH2289: 0 | AI2289: 0 | AJ2289: 0
A2290: 251-9012484 | B2290: =VLOOKUP(A2290,Sheet3!A:B,2,0) -> INV-201-2767 | C2290: Invoice | D2290: 67070 | E2290: BE-LIGHT MANGO 1.5L/6PK | F2290: BE-LIGHT | G2290: BEBIDAS | H2290: BEBIDA CON SABOR | I2290: BEBIDA CON SABOR | J2290: BEBIDA CON SABOR | K2290: 11729 | L2290: Castillo Market LLC | M2290: 251 - Manuel Ayala | N2290: 201 | O2290: Manuel Ayala | P2290: Sunmex Truck - 153 | Q2290: 103 | R2290: 02/17/2026 | S2290: 02 | T2290: 2026 | U2290: 6 | V2290: 6 | W2290: UNIT(S) | X2290: 1.99 | Y2290: 1.49 | Z2290: 0 | AA2290: 11.94 | AB2290: 25.13% | AC2290: 0 | AD2290: 0 | AE2290: 0 | AF2290: 0 | AG2290: 6 | AH2290: 0 | AI2290: 0 | AJ2290: 0
A2291: 255-9010979 | B2291: =VLOOKUP(A2291,Sheet3!A:B,2,0) -> INV-205-2971 | C2291: Invoice | D2291: 21581 | E2291: GAMESA EMPERADR COMBINADO 109G | F2291: GAMESA | G2291: GALLETAS | H2291: GALLETAS DULCES | I2291: ------ | J2291: ------ | K2291: 10168 | L2291: Arco / Mini Mart | M2291: 255 - Carlos Morales | N2291: 205 | O2291: Carlos Morales | P2291: Sunmex Truck - 159 | Q2291: 105 | R2291: 02/17/2026 | S2291: 02 | T2291: 2026 | U2291: 5 | V2291: 5 | W2291: UNIT(S) | X2291: 2.09 | Y2291: 1.4 | Z2291: 0 | AA2291: 10.45 | AB2291: 33.01% | AC2291: 0 | AD2291: 0 | AE2291: 0 | AF2291: 0 | AG2291: 5 | AH2291: 0 | AI2291: 0 | AJ2291: 0
A2292: 256-9009436 | B2292: =VLOOKUP(A2292,Sheet3!A:B,2,0) -> INV-206-3025 | C2292: Invoice | D2292: 16190 | E2292: JUMEX PRISM PEACH 33.81/12CT | F2292: JUMEX | G2292: BEBIDAS | H2292: JUGO DE FRUTAS | I2292: JUGO DE FRUTAS | J2292: JUGO DE FRUTAS | K2292: 10599 | L2292: El Rancho Barajas LLC | M2292: 256 - Ana Ibarra | N2292: 206 | O2292: Ana Ibarra | P2292: Sunmex Truck - 156 | Q2292: 104 | R2292: 02/17/2026 | S2292: 02 | T2292: 2026 | U2292: 12 | V2292: 12 | W2292: UNIT(S) | X2292: 1.79 | Y2292: 1.23 | Z2292: 0 | AA2292: 21.48 | AB2292: 31.28% | AC2292: 0 | AD2292: 0 | AE2292: 0 | AF2292: 0 | AG2292: 12 | AH2292: 0 | AI2292: 0 | AJ2292: 0
A2293: 256-9009437 | B2293: =VLOOKUP(A2293,Sheet3!A:B,2,0) -> INV-206-3026 | C2293: Invoice | D2293: 31064 | E2293: SAB DORITO NACHOS 146G | F2293: SABRITAS | G2293: BOTANAS | H2293: MAIZ | I2293: CON QUESO | J2293: CON CHILE | K2293: 10643 | L2293: Food City #021 | M2293: 256 - Ana Ibarra | N2293: 206 | O2293: Ana Ibarra | P2293: Sunmex Truck - 156 | Q2293: 104 | R2293: 02/17/2026 | S2293: 02 | T2293: 2026 | U2293: 10 | V2293: 10 | W2293: UNIT(S) | X2293: 2.99 | Y2293: 1.99 | Z2293: 0 | AA2293: 29.9 | AB2293: 26.76% | AC2293: -2 | AD2293: 0 | AE2293: 0 | AF2293: 0 | AG2293: 10 | AH2293: 0 | AI2293: 0 | AJ2293: 0
A2294: 254-9011980 | B2294: =VLOOKUP(A2294,Sheet3!A:B,2,0) -> INV-204-2919 | C2294: Invoice | D2294: 30920 | E2294: SAB CHETO BOLITAS 110G | F2294: SABRITAS | G2294: BOTANAS | H2294: MAIZ | I2294: CON QUESO | J2294: CON CHILE | K2294: 10174 | L2294: Arco #82831 | M2294: 254 - Yurithzin Perez | N2294: 204 | O2294: Yurithzin Perez | P2294: Sunmex Truck - 151 | Q2294: 101 | R2294: 02/17/2026 | S2294: 02 | T2294: 2026 | U2294: 5 | V2294: 5 | W2294: UNIT(S) | X2294: 2.79 | Y2294: 1.99 | Z2294: 0 | AA2294: 13.95 | AB2294: 28.67% | AC2294: 0 | AD2294: 0 | AE2294: 0 | AF2294: 0 | AG2294: 5 | AH2294: 0 | AI2294: 0 | AJ2294: 0
A2295: 251-9012480 | B2295: =VLOOKUP(A2295,Sheet3!A:B,2,0) -> INV-201-2763 | C2295: Invoice | D2295: 55022 | E2295: SAB PAKETAXO MORADO 215G | F2295: SABRITAS | G2295: BOTANAS | H2295: PAPAS | I2295: ------ | J2295: ------ | K2295: 11500 | L2295: Wintersburg General Store | M2295: 251 - Manuel Ayala | N2295: 201 | O2295: Manuel Ayala | P2295: Sunmex Truck - 153 | Q2295: 103 | R2295: 02/17/2026 | S2295: 02 | T2295: 2026 | U2295: 5 | V2295: 5 | W2295: UNIT(S) | X2295: 4.29 | Y2295: 3.05 | Z2295: 0 | AA2295: 21.45 | AB2295: 28.9% | AC2295: 0 | AD2295: 0 | AE2295: 0 | AF2295: 0 | AG2295: 5 | AH2295: 0 | AI2295: 0 | AJ2295: 0
A2296: 354-9001489 | B2296: =VLOOKUP(A2296,Sheet3!A:B,2,0) -> INV-251-3074 | C2296: Invoice | D2296: 30937 | E2296: SAB CHETO FLAMIN HOT 145G | F2296: SABRITAS | G2296: BOTANAS | H2296: MAIZ | I2296: CON QUESO | J2296: CON CHILE | K2296: 10648 | L2296: Food City #060 | M2296: 354 - Joa Ibarra | N2296: 251 | O2296: Joa Ibarra | P2296: Sunmex Truck - 351 | Q2296: 102 | R2296: 02/17/2026 | S2296: 02 | T2296: 2026 | U2296: 30 | V2296: 30 | W2296: UNIT(S) | X2296: 2.99 | Y2296: 1.99 | Z2296: 0 | AA2296: 89.7 | AB2296: 26.76% | AC2296: -6 | AD2296: 0 | AE2296: 0 | AF2296: 0 | AG2296: 30 | AH2296: 0 | AI2296: 0 | AJ2296: 0
A2297: 254-9011984 | B2297: =VLOOKUP(A2297,Sheet3!A:B,2,0) -> INV-204-2922 | C2297: Invoice | D2297: 51062 | E2297: SAB FRITO CHORIZO 170G | F2297: SABRITAS | G2297: BOTANAS | H2297: MAIZ | I2297: CON CHORIZO | J2297: CON CHIPOTLE | K2297: 10647 | L2297: Food City #041 | M2297: 254 - Yurithzin Perez | N2297: 204 | O2297: Yurithzin Perez | P2297: Sunmex Truck - 151 | Q2297: 101 | R2297: 02/17/2026 | S2297: 02 | T2297: 2026 | U2297: 10 | V2297: 10 | W2297: UNIT(S) | X2297: 2.99 | Y2297: 1.99 | Z2297: 0 | AA2297: 29.9 | AB2297: 26.76% | AC2297: -2 | AD2297: 0 | AE2297: 0 | AF2297: 0 | AG2297: 10 | AH2297: 0 | AI2297: 0 | AJ2297: 0
A2298: 254-9011987 | B2298: =VLOOKUP(A2298,Sheet3!A:B,2,0) -> INV-204-2924 | C2298: Invoice | D2298: 27830 | E2298: GUMM PALETA ROSA 3.52OZ/6CT | F2298: GUMMY BEAR DIST | G2298: DULCES | H2298: PEG | I2298: PALETAS DULCES | J2298: ------ | K2298: 11526 | L2298: Grab and Go Convenience Market | M2298: 254 - Yurithzin Perez | N2298: 204 | O2298: Yurithzin Perez | P2298: Sunmex Truck - 151 | Q2298: 101 | R2298: 02/17/2026 | S2298: 02 | T2298: 2026 | U2298: 6 | V2298: 6 | W2298: UNIT(S) | X2298: 2.29 | Y2298: 1.49 | Z2298: 0 | AA2298: 13.74 | AB2298: 34.93% | AC2298: 0 | AD2298: 0 | AE2298: 0 | AF2298: 0 | AG2298: 6 | AH2298: 0 | AI2298: 0 | AJ2298: 0
A2299: 255-9010979 | B2299: =VLOOKUP(A2299,Sheet3!A:B,2,0) -> INV-205-2971 | C2299: Invoice | D2299: 30876 | E2299: SAB TOSTITO FLAMIN H 175G | F2299: SABRITAS | G2299: BOTANAS | H2299: MAIZ | I2299: CON CHILE | J2299: CON SABOR | K2299: 10168 | L2299: Arco / Mini Mart | M2299: 255 - Carlos Morales | N2299: 205 | O2299: Carlos Morales | P2299: Sunmex Truck - 159 | Q2299: 105 | R2299: 02/17/2026 | S2299: 02 | T2299: 2026 | U2299: 5 | V2299: 5 | W2299: UNIT(S) | X2299: 2.79 | Y2299: 1.99 | Z2299: 0 | AA2299: 13.95 | AB2299: 28.67% | AC2299: 0 | AD2299: 0 | AE2299: 0 | AF2299: 0 | AG2299: 5 | AH2299: 0 | AI2299: 0 | AJ2299: 0
... A2366: 253-9015797 | B2366: =VLOOKUP(A2366,Sheet3!A:B,2,0) -> INV-203-2865 | C2366: Invoice | D2366: 30876 | E2366: SAB TOSTITO FLAMIN H 175G | F2366: SABRITAS | G2366: BOTANAS | H2366: MAIZ | I2366: CON CHILE | J2366: CON SABOR | K2366: 10652 | L2366: Food City #089 | M2366: 253 - Balbina Rodriguez | N2366: 203 | O2366: Balbina Rodriguez | P2366: Sunmex Truck - 161 | Q2366: 106 | R2366: 02/17/2026 | S2366: 02 | T2366: 2026 | U2366: 5 | V2366: 5 | W2366: UNIT(S) | X2366: 2.99 | Y2366: 1.99 | Z2366: 0 | AA2366: 14.95 | AB2366: 26.76% | AC2366: -1 | AD2366: 0 | AE2366: 0 | AF2366: 0 | AG2366: 5 | AH2366: 0 | AI2366: 0 | AJ2366: 0
A2367: 259-9000560 | B2367: =VLOOKUP(A2367,Sheet3!A:B,2,0) -> INV-001-3055 | C2367: Invoice | D2367: 82417 | E2367: SAB CHETO COLMILLOS 100G | F2367: SABRITAS | G2367: BOTANAS | H2367: MAIZ | I2367: CON QUESO | J2367: CON CHILE | K2367: 11719 | L2367: NC Distributor LLC. | M2367: 259 - Venta Administrativa | N2367: 001 | O2367: Ventas Administrativas | P2367: Sunmex Truck - 152 | Q2367: 001 | R2367: 02/17/2026 | S2367: 02 | T2367: 2026 | U2367: 140 | V2367: 140 | W2367: UNIT(S) | X2367: 2.1 | Y2367: 1.99 | Z2367: 0 | AA2367: 294 | AB2367: 38.1% | AC2367: 96.6 | AD2367: 0 | AE2367: 0 | AF2367: 0 | AG2367: 140 | AH2367: 0 | AI2367: 0 | AJ2367: 0
A2368: 254-9011989 | B2368: =VLOOKUP(A2368,Sheet3!A:B,2,0) -> INV-204-2926 | C2368: Invoice | D2368: 67650 | E2368: SAB PAPA ORIGINAL SAL 120G | F2368: SABRITAS | G2368: BOTANAS | H2368: PAPAS | I2368: CON SAL | J2368: ------ | K2368: 11245 | L2368: Speedy Market | M2368: 254 - Yurithzin Perez | N2368: 204 | O2368: Yurithzin Perez | P2368: Sunmex Truck - 151 | Q2368: 101 | R2368: 02/17/2026 | S2368: 02 | T2368: 2026 | U2368: 5 | V2368: 5 | W2368: UNIT(S) | X2368: 2.79 | Y2368: 1.99 | Z2368: 0 | AA2368: 13.95 | AB2368: 28.67% | AC2368: 0 | AD2368: 0 | AE2368: 0 | AF2368: 0 | AG2368: 5 | AH2368: 0 | AI2368: 0 | AJ2368: 0
A2369: 255-9010988 | B2369: =VLOOKUP(A2369,Sheet3!A:B,2,0) -> INV-205-2979 | C2369: Invoice | D2369: 19209 | E2369: PARR ALOE MANGO 500ML/20CT | F2369: PARROT | G2369: BEBIDAS | H2369: JUGO DE FRUTAS | I2369: ALOE VERA | J2369: JUGO DE FRUTAS | K2369: 11144 | L2369: Quick Stop / Mcdowell | M2369: 255 - Carlos Morales | N2369: 205 | O2369: Carlos Morales | P2369: Sunmex Truck - 159 | Q2369: 105 | R2369: 02/17/2026 | S2369: 02 | T2369: 2026 | U2369: 20 | V2369: 20 | W2369: UNIT(S) | X2369: 1.29 | Y2369: 0.86 | Z2369: 0 | AA2369: 25.8 | AB2369: 33.33% | AC2369: 0 | AD2369: 0 | AE2369: 0 | AF2369: 0 | AG2369: 20 | AH2369: 0 | AI2369: 0 | AJ2369: 0
A2370: 255-9010982 | B2370: =VLOOKUP(A2370,Sheet3!A:B,2,0) -> INV-205-2974 | C2370: Invoice | D2370: 22502 | E2370: GAMESA EMPERADOR PIRUETA 115G | F2370: GAMESA | G2370: GALLETAS | H2370: GALLETAS DULCES | I2370: ------ | J2370: ------ | K2370: 10444 | L2370: Chevron #355144 | M2370: 255 - Carlos Morales | N2370: 205 | O2370: Carlos Morales | P2370: Sunmex Truck - 159 | Q2370: 105 | R2370: 02/17/2026 | S2370: 02 | T2370: 2026 | U2370: 5 | V2370: 5 | W2370: UNIT(S) | X2370: 2.09 | Y2370: 1.4 | Z2370: 0 | AA2370: 10.45 | AB2370: 33.01% | AC2370: 0 | AD2370: 0 | AE2370: 0 | AF2370: 0 | AG2370: 5 | AH2370: 0 | AI2370: 0 | AJ2370: 0
A2371: 251-9012483 | B2371: =VLOOKUP(A2371,Sheet3!A:B,2,0) -> INV-201-2766 | C2371: Invoice | D2371: 12559 | E2371: SAB CHURRUM LIMON 185G | F2371: SABRITAS | G2371: BOTANAS | H2371: MAIZ | I2371: CON CHILE | J2371: CON LIMON | K2371: 11185 | L2371: Saguaro Market | M2371: 251 - Manuel Ayala | N2371: 201 | O2371: Manuel Ayala | P2371: Sunmex Truck - 153 | Q2371: 103 | R2371: 02/17/2026 | S2371: 02 | T2371: 2026 | U2371: 10 | V2371: 10 | W2371: UNIT(S) | X2371: 2.79 | Y2371: 1.99 | Z2371: 0 | AA2371: 27.9 | AB2371: 28.67% | AC2371: 0 | AD2371: 0 | AE2371: 0 | AF2371: 0 | AG2371: 10 | AH2371: 0 | AI2371: 0 | AJ2371: 0
A2372: 251-9012483 | B2372: =VLOOKUP(A2372,Sheet3!A:B,2,0) -> INV-201-2766 | C2372: Invoice | D2372: 32295 | E2372: SUEROX MORA AZUL 630ML/12CT | F2372: SUEROX | G2372: BEBIDAS | H2372: SUERO | I2372: ------ | J2372: ------ | K2372: 11185 | L2372: Saguaro Market | M2372: 251 - Manuel Ayala | N2372: 201 | O2372: Manuel Ayala | P2372: Sunmex Truck - 153 | Q2372: 103 | R2372: 02/17/2026 | S2372: 02 | T2372: 2026 | U2372: 24 | V2372: 24 | W2372: UNIT(S) | X2372: 1.6658 | Y2372: 1.17 | Z2372: 0 | AA2372: 39.9792 | AB2372: 29.76% | AC2372: 0 | AD2372: 0 | AE2372: 0 | AF2372: 0 | AG2372: 24 | AH2372: 0 | AI2372: 0 | AJ2372: 0
A2373: 255-9010978 | B2373: =VLOOKUP(A2373,Sheet3!A:B,2,0) -> INV-205-2970 | C2373: Invoice | D2373: 67667 | E2373: SAB PAPA ADOBADA 105G | F2373: SABRITAS | G2373: BOTANAS | H2373: PAPAS | I2373: CON ADOBO | J2373: CON SABOR | K2373: 11829 | L2373: Chevron Extra Mile / 7th St | M2373: 255 - Carlos Morales | N2373: 205 | O2373: Carlos Morales | P2373: Sunmex Truck - 151 | Q2373: 101 | R2373: 02/17/2026 | S2373: 02 | T2373: 2026 | U2373: 5 | V2373: 5 | W2373: UNIT(S) | X2373: 2.79 | Y2373: 1.99 | Z2373: 0 | AA2373: 13.95 | AB2373: 28.67% | AC2373: 0 | AD2373: 0 | AE2373: 0 | AF2373: 0 | AG2373: 5 | AH2373: 0 | AI2373: 0 | AJ2373: 0
A2374: 255-9010980 | B2374: =VLOOKUP(A2374,Sheet3!A:B,2,0) -> INV-205-2972 | C2374: Invoice | D2374: 13205 | E2374: BARCEL BIG MIX INGLES 75G | F2374: BARCEL | G2374: BOTANAS | H2374: ------ | I2374: ------ | J2374: ------ | K2374: 10168 | L2374: Arco / Mini Mart | M2374: 255 - Carlos Morales | N2374: 205 | O2374: Carlos Morales | P2374: Sunmex Truck - 159 | Q2374: 105 | R2374: 02/17/2026 | S2374: 02 | T2374: 2026 | U2374: 5 | V2374: 5 | W2374: UNIT(S) | X2374: 2.29 | Y2374: 1.5 | Z2374: 0 | AA2374: 11.45 | AB2374: 34.5% | AC2374: 0 | AD2374: 0 | AE2374: 0 | AF2374: 0 | AG2374: 5 | AH2374: 0 | AI2374: 0 | AJ2374: 0
...

Sheet CREDITOS
A1: Reference | B1: number | C1: Document | D1: sku | E1: Product | F1: Brand | G1: Type | H1: Family | I1: Line | J1: Sub Line | K1: clientNumber | L1: Customer | M1: Route Name | N1: routeVendor | O1: Sales Rep | P1: Truck Name | Q1: routeDriver | R1: returnedAt | S1: Month | T1: Year | U1: Orig. Qty. | V1: Quantity | W1: Unit | X1: actualCost | Y1: Cost | Z1: Total Weight | AA1: Sale | AB1: Margin | AC1: Discount (Promotions) | AD1: out of code | AE1: Good Return | AF1: No Charge | AG1: Sale Units | AH1: creditMemo | AI1: goodReturn | AJ1: noCost
A2: 255-9010974 | B2: CRM-205-1952 | C2: Invoice | D2: 51086 | E2: SAB SABRITONES 160G | F2: SABRITAS | G2: BOTANAS | H2: CHICHARRONES | I2: CON CHILE | J2: CON LIMON | K2: 10406 | L2: Chevron #093679 | M2: 255 - Carlos Morales | N2: 205 | O2: Carlos Morales | P2: Sunmex Truck - 156 | Q2: 104 | R2: 02/16/2026 | S2: 02 | T2: 2026 | U2: 1 | V2: 1 | W2: UNIT(S) | X2: 3.29 | Y2: 1.99 | Z2: 0 | AA2: 0 | AB2: 0 | AC2: 0 | AD2: 3.29 | AE2: 0 | AF2: 0 | AG2: 0 | AH2: 1 | AI2: 0 | AJ2: 0
A3: 255-9010974 | B3: CRM-205-1952 | C3: Invoice | D3: 24038 | E3: PARR CAN POMEGRANATE 485/12CT | F3: PARROT | G3: BEBIDAS | H3: JUGO DE FRUTAS | I3: AGUA DE COCO | J3: JUGO DE FRUTAS | K3: 10406 | L3: Chevron #093679 | M3: 255 - Carlos Morales | N3: 205 | O3: Carlos Morales | P3: Sunmex Truck - 156 | Q3: 104 | R3: 02/16/2026 | S3: 02 | T3: 2026 | U3: 12 | V3: 12 | W3: UNIT(S) | X3: 1.583 | Y3: 0.94583 | Z3: 0 | AA3: 0 | AB3: 0 | AC3: 0 | AD3: 0 | AE3: 18.996 | AF3: 0 | AG3: 0 | AH3: 0 | AI3: 12 | AJ3: 0
A4: 255-9010975 | B4: CRM-205-1953 | C4: Invoice | D4: 14517 | E4: SAB RANCHERITOS 145G | F4: SABRITAS | G4: BOTANAS | H4: MAIZ | I4: CON CHILE | J4: CON SABOR | K4: 11226 | L4: PVM Sinclair | M4: 255 - Carlos Morales | N4: 205 | O4: Carlos Morales | P4: Sunmex Truck - 156 | Q4: 104 | R4: 02/16/2026 | S4: 02 | T4: 2026 | U4: 1 | V4: 1 | W4: UNIT(S) | X4: 2.49 | Y4: 1.99 | Z4: 0 | AA4: 0 | AB4: 0 | AC4: 0 | AD4: 2.49 | AE4: 0 | AF4: 0 | AG4: 0 | AH4: 1 | AI4: 0 | AJ4: 0
A5: 255-9010975 | B5: CRM-205-1953 | C5: Invoice | D5: 25541 | E5: SAB FAM DORITO MIX 205G | F5: SABRITAS | G5: BOTANAS | H5: ------ | I5: ------ | J5: ------ | K5: 11226 | L5: PVM Sinclair | M5: 255 - Carlos Morales | N5: 205 | O5: Carlos Morales | P5: Sunmex Truck - 156 | Q5: 104 | R5: 02/16/2026 | S5: 02 | T5: 2026 | U5: 4 | V5: 4 | W5: UNIT(S) | X5: 4.29 | Y5: 3.05 | Z5: 0 | AA5: 0 | AB5: 0 | AC5: 0 | AD5: 17.16 | AE5: 0 | AF5: 0 | AG5: 0 | AH5: 4 | AI5: 0 | AJ5: 0
A6: 255-9010977 | B6: CRM-205-1954 | C6: Invoice | D6: 55008 | E6: SAB PAKETAXO AZUL 208G | F6: SABRITAS | G6: BOTANAS | H6: PAPAS | I6: ------ | J6: ------ | K6: 11329 | L6: Stop & Shop | M6: 255 - Carlos Morales | N6: 205 | O6: Carlos Morales | P6: Sunmex Truck - 156 | Q6: 104 | R6: 02/16/2026 | S6: 02 | T6: 2026 | U6: 2 | V6: 2 | W6: UNIT(S) | X6: 4.29 | Y6: 3.05 | Z6: 0 | AA6: 0 | AB6: 0 | AC6: 0 | AD6: 8.58 | AE6: 0 | AF6: 0 | AG6: 0 | AH6: 2 | AI6: 0 | AJ6: 0
A7: 255-9010977 | B7: CRM-205-1954 | C7: Invoice | D7: 51062 | E7: SAB FRITO CHORIZO 170G | F7: SABRITAS | G7: BOTANAS | H7: MAIZ | I7: CON CHORIZO | J7: CON CHIPOTLE | K7: 11329 | L7: Stop & Shop | M7: 255 - Carlos Morales | N7: 205 | O7: Carlos Morales | P7: Sunmex Truck - 156 | Q7: 104 | R7: 02/16/2026 | S7: 02 | T7: 2026 | U7: 4 | V7: 4 | W7: UNIT(S) | X7: 2.79 | Y7: 1.99 | Z7: 0 | AA7: 0 | AB7: 0 | AC7: 0 | AD7: 11.16 | AE7: 0 | AF7: 0 | AG7: 0 | AH7: 4 | AI7: 0 | AJ7: 0
A8: 255-9010977 | B8: CRM-205-1954 | C8: Invoice | D8: 66234 | E8: BARCEL CHIP JALAPENO 170G | F8: BARCEL | G8: BOTANAS | H8: PAPAS | I8: CON SABOR | J8: ------ | K8: 11329 | L8: Stop & Shop | M8: 255 - Carlos Morales | N8: 205 | O8: Carlos Morales | P8: Sunmex Truck - 156 | Q8: 104 | R8: 02/16/2026 | S8: 02 | T8: 2026 | U8: 3 | V8: 3 | W8: UNIT(S) | X8: 5.19 | Y8: 3.45 | Z8: 0 | AA8: 0 | AB8: 0 | AC8: 0 | AD8: 15.57 | AE8: 0 | AF8: 0 | AG8: 0 | AH8: 3 | AI8: 0 | AJ8: 0
A9: 254-9011977 | B9: CRM-204-1931 | C9: Invoice | D9: 41729 | E9: DIANDI CANDLE SPARK BLUE SPANISH | F9: VIG PARTY | G9: ABARROTES | H9: VELAS | I9: ------ | J9: ------ | K9: 10104 | L9: Speedway Liquor | M9: 254 - Yurithzin Perez | N9: 204 | O9: Yurithzin Perez | P9: Sunmex Truck - 156 | Q9: 104 | R9: 02/16/2026 | S9: 02 | T9: 2026 | U9: 7 | V9: 7 | W9: UNIT(S) | X9: 2.99 | Y9: 1.86 | Z9: 0 | AA9: 0 | AB9: 0 | AC9: 0 | AD9: 20.93 | AE9: 0 | AF9: 0 | AG9: 0 | AH9: 7 | AI9: 0 | AJ9: 0
A10: 251-9012469 | B10: CRM-201-1865 | C10: Invoice | D10: 13907 | E10: DIANDI COYOTA DUL LECH 9.52/14CT | F10: DIANDI | G10: PANES | H10: COYOTAS | I10: RELLENOS | J10: DULCE DE LECHE | K10: 10672 | L10: Food City #140 | M10: 251 - Manuel Ayala | N10: 201 | O10: Manuel Ayala | P10: Sunmex Truck - 153 | Q10: 103 | R10: 02/16/2026 | S10: 02 | T10: 2026 | U10: 7 | V10: 7 | W10: UNIT(S) | X10: 2.35 | Y10: 1.68 | Z10: 0 | AA10: 0 | AB10: 0 | AC10: 0 | AD10: 16.45 | AE10: 0 | AF10: 0 | AG10: 0 | AH10: 7 | AI10: 0 | AJ10: 0
A11: 251-9012471 | B11: CRM-201-1866 | C11: Invoice | D11: 31118 | E11: SAB FRITO CHILE LIMON 170G | F11: SABRITAS | G11: BOTANAS | H11: MAIZ | I11: CON CHILE | J11: CON LIMON | K11: 10672 | L11: Food City #140 | M11: 251 - Manuel Ayala | N11: 201 | O11: Manuel Ayala | P11: Sunmex Truck - 153 | Q11: 103 | R11: 02/16/2026 | S11: 02 | T11: 2026 | U11: 7 | V11: 7 | W11: UNIT(S) | X11: 2.99 | Y11: 1.99 | Z11: 0 | AA11: 0 | AB11: 0 | AC11: 0 | AD11: 20.93 | AE11: 0 | AF11: 0 | AG11: 0 | AH11: 7 | AI11: 0 | AJ11: 0
A12: 251-9012471 | B12: CRM-201-1866 | C12: Invoice | D12: 31125 | E12: SAB FRITO LIMON SAL 170G | F12: SABRITAS | G12: BOTANAS | H12: MAIZ | I12: CON SAL | J12: CON LIMON | K12: 10672 | L12: Food City #140 | M12: 251 - Manuel Ayala | N12: 201 | O12: Manuel Ayala | P12: Sunmex Truck - 153 | Q12: 103 | R12: 02/16/2026 | S12: 02 | T12: 2026 | U12: 12 | V12: 12 | W12: UNIT(S) | X12: 2.99 | Y12: 1.99 | Z12: 0 | AA12: 0 | AB12: 0 | AC12: 0 | AD12: 35.88 | AE12: 0 | AF12: 0 | AG12: 0 | AH12: 12 | AI12: 0 | AJ12: 0
A13: 255-9010972 | B13: CRM-205-1951 | C13: Invoice | D13: 30682 | E13: SAB FAM RUFFLE MIX 170G | F13: SABRITAS | G13: BOTANAS | H13: ------ | I13: ------ | J13: ------ | K13: 11899 | L13: Sinclair/Washington | M13: 255 - Carlos Morales | N13: 205 | O13: Carlos Morales | P13: Sunmex Truck - 151 | Q13: 101 | R13: 02/16/2026 | S13: 02 | T13: 2026 | U13: 1 | V13: 1 | W13: UNIT(S) | X13: 4.29 | Y13: 3.05 | Z13: 0 | AA13: 0 | AB13: 0 | AC13: 0 | AD13: 4.29 | AE13: 0 | AF13: 0 | AG13: 0 | AH13: 1 | AI13: 0 | AJ13: 0
... A582: 252-010830 | B582: CRM-202-1882 | C582: Credit Memo | D582: 13860 | E582: DIANDI COYOTA JAMONCIL 9.52/14CT | F582: DIANDI | G582: PANES | H582: COYOTAS | I582: RELLENOS | J582: JAMONCILLO | K582: 10659 | L582: Food City #105 | M582: 252 - Daisy Burciaga | N582: 202 | O582: Daisy Burciaga | P582: Sunmex Truck - 153 | Q582: 103 | R582: 02/20/2026 | S582: 02 | T582: 2026 | U582: 1 | V582: 1 | W582: UNIT(S) | X582: 2.35 | Y582: 1.68 | Z582: 0 | AA582: 0 | AB582: 0 | AC582: 0 | AD582: 2.35 | AE582: 0 | AF582: 0 | AG582: 0 | AH582: 1 | AI582: 0 | AJ582: 0

Sheet Sheet3
A3: Row Labels
A4: 251-9012470 | B4: INV-201-2757
A5: 251-9012474 | B5: INV-201-2758
A6: 251-9012475 | B6: INV-201-2759
A7: 251-9012476 | B7: INV-201-2760
A8: 251-9012477 | B8: INV-201-2761
A9: 251-9012479 | B9: INV-201-2762
A10: 251-9012480 | B10: INV-201-2763
A11: 251-9012481 | B11: INV-201-2764
A12: 251-9012482 | B12: INV-201-2765
A13: 251-9012483 | B13: INV-201-2766
A14: 251-9012484 | B14: INV-201-2767
A15: 251-9012485 | B15: INV-201-2768
... A331: 381-000762 | B331: INV-252-3084
A332: (blank)
A333: Grand Total

Sheet Sheet2
A3: Row Labels
A4: 251-9012469 | B4: CRM-201-1865
A5: 251-9012471 | B5: CRM-201-1866
A6: 251-9012472 | B6: CRM-201-1867
A7: 251-9012473 | B7: CRM-201-1868
A8: 251-9012477 | B8: CRM-201-1869
A9: 251-9012478 | B9: CRM-201-1870
A10: 251-9012481 | B10: CRM-201-1871
A11: 251-9012483 | B11: CRM-201-1872
A12: 251-9012488 | B12: CRM-201-1873
A13: 251-9012492 | B13: CRM-201-1874
A14: 251-9012504 | B14: CRM-201-1875
A15: 251-9012505 | B15: CRM-201-1876
... A150: 381-000757 | B150: CRM-252-2011
A151: (blank)
A152: Grand Total
